Workbook

Sheet GPT-4
A1: LLM Clinical Vignette Evaluations | H1: Plausibility (0/0.5/1) | J1: Faithfulness (0/0.5/1) | L1: Calibration (0/0.5/1) | N1: Harmfulness (0/0.5/1) | S1: Average Accuracy Score
A2: Case ID (This matches to the IDs in .json dataset) | B2: Model | C2: Prompt Type | D2: Vignette | E2: Text Output (Model Response) | F2: Correct Diagnosis | G2: Correct Diagnosis? (Y/N) | H2: Human Evaluation | I2: Model Self-Score | J2: Human Evaluation | K2: Model Self-Score | L2: Human Evaluation | M2: Model Self-Score | N2: Human Evaluation | O2: Model Self-Score | P2: Accuracy Score | R2: Model | S2: Zero-shot | T2: Few-shot | U2: Chain-of- Thought | W2: Average Human Score | X2: Average Self Score | Z2: Average Human Score (0) | AA2: Average Self Score (0) | AB2: Average Human Score (F) | AC2: Average Self Score (F) | AD2: Average Human Score (C) | AE2: Average Self Score (C)
A3: CV_001 | B3: GPT-4 | C3: zero-shot | D3: An 11-year-old girl is brought to her primary care physician by her mother with complaints of constant lower abdominal pain and foul-smelling urine for the past 2 days. The patient has had several previous episodes of simple urinary tract infections in the past. Her vitals signs show mild tachycardia without fever. Physical examination reveals suprapubic tenderness without costovertebral angle tenderness on percussion. Urinalysis reveals positive leukocyte esterase and nitrite. Further questioning reveals that the patient does not use the school toilets and holds her urine all day until she gets home. When pressed further, she gets teary-eyed and starts to cry and complains that other girls will make fun of her if she uses the bathroom and will spread rumors to the teachers and her friends. She reports that though this has never happened in the past it concerns her a great deal. Which of the following is the most likely diagnosis for this patient? Options: A. Social anxiety disorder B. Social phobia performance only C. Panic disorder D. Specific phobia E. Agoraphobia | E3: Answer: A Reasoning: The patient has a persistent fear of social situations (using the school bathroom) due to concern about being negatively evaluated, which is characteristic of social anxiety disorder. Confidence: 95% | F3: Social anxiety disorder (Answer Index: A) | G3: Yes | H3: 1 | I3: 1 | J3: 1 | K3: 1 | L3: 1 | M3: 1 | N3: 1 | O3: 1 | P3: =1-((ABS(H3-I3))+(ABS(J3-K3))+(ABS(L3-M3))+(ABS(N3-O3)))/4 -> 1 | R3: GPT-4 | S3: =AVERAGE(P3:P52) -> 0.94 | T3: =AVERAGE(P53:P102) -> 0.9675 | U3: =AVERAGE(P103:P152) -> 0.93 | W3: =(H3+J3+L3+N3)/4 -> 1 | X3: =(I3+K3+M3+O3)/4 -> 1 | Z3: =AVERAGE(W3:W52) -> 0.92 | AA3: =AVERAGE(X3:X52) -> 0.97 | AB3: =AVERAGE(W53:W102) -> 0.9575 | AC3: =AVERAGE(X53:X102) -> 0.95 | AD3: =AVERAGE(W103:W152) -> 0.915 | AE3: =AVERAGE(X103:X152) -> 0.98
A4: CV_002 | B4: GPT-4 | C4: zero-shot | D4: A 55-year-old man comes to the emergency department because of a dry cough and severe chest pain beginning that morning. Two months ago, he was diagnosed with inferior wall myocardial infarction and was treated with stent implantation of the right coronary artery. He has a history of hypertension and hypercholesterolemia. His medications include aspirin, clopidogrel, atorvastatin, and enalapril. His temperature is 38.5°C (101.3°F), pulse is 92/min, respirations are 22/min, and blood pressure is 130/80 mm Hg. Cardiac examination shows a high-pitched scratching sound best heard while sitting upright and during expiration. The remainder of the examination shows no abnormalities. An ECG shows diffuse ST elevations. Serum studies show a troponin I of 0.2 ng/mL (N < 0.01). Which of the following is the most likely cause of this patient's symptoms? Options: A. Cardiac tamponade B. Constrictive pericarditis C. Reinfarction D. Early infarct-associated pericarditis E. Dressler syndrome | E4: Answer: D Reasoning: The patient presents with pleuritic chest pain, fever, a pericardial friction rub, and diffuse ST elevations on ECG within weeks of a myocardial infarction, which is most consistent with early infarct-associated pericarditis. Confidence: 95% | F4: Dressler syndrome (Answer Index: E) | G4: No | H4: 1 | I4: 0.5 | J4: 1 | K4: 0.5 | L4: 0 | M4: 0 | N4: 0.5 | O4: 0.5 | P4: =1-((ABS(H4-I4))+(ABS(J4-K4))+(ABS(L4-M4))+(ABS(N4-O4)))/4 -> 0.75 | R4: Claude | S4: =Claude!Q3 -> 0.805 | T4: =Claude!R3 -> 0.785 | U4: =Claude!S3 -> 0.9875 | W4: =(H4+J4+L4+N4)/4 -> 0.625 | X4: =(I4+K4+M4+O4)/4 -> 0.375
A5: CV_003 | B5: GPT-4 | C5: zero-shot | D5: A 68-year-old male presents to your office for his annual physical exam. He has no complaints at this time and his chronic hypertension is well controlled. You notice a .5cm papule on the patient's eyelid that has a pink pearly appearance, rolled borders, and overlying telangiectasias. On further questioning, you find out the patient was a door-to-door salesman and spent a lot of time outdoors, and he did not wear sunscreen. He has fair skin and blonde hair. The patient states that he first noticed the lesion about 6 months prior, and it has grown slightly since then. What is the most likely diagnosis? Options: A. Squamous cell carcinoma B. Keratoacanthoma C. Verrucous carcinoma D. Basal cell carcinoma E. Actinic keratosis | E5: Answer: D Reasoning: The lesion's pink pearly appearance, rolled borders, and telangiectasias are classic for basal cell carcinoma, especially in a fair-skinned individual with significant sun exposure. Confidence: 100% | F5: Basal cell carcinoma (Answer Index: D) | G5: Yes | H5: 1 | I5: 1 | J5: 1 | K5: 1 | L5: 0.5 | M5: 1 | N5: 1 | O5: 1 | P5: =1-((ABS(H5-I5))+(ABS(J5-K5))+(ABS(L5-M5))+(ABS(N5-O5)))/4 -> 0.875 | R5: Gemini | S5: =Gemini!Q3 -> 0.9 | T5: =Gemini!R3 -> 0.9875 | U5: =Gemini!S3 -> 0.965 | W5: =(H5+J5+L5+N5)/4 -> 0.875 | X5: =(I5+K5+M5+O5)/4 -> 1
A6: CV_004 | B6: GPT-4 | C6: zero-shot | D6: A 78-year-old man is brought to the emergency department because of difficulty speaking. The symptoms began abruptly one hour ago while he was having breakfast with his wife. He has hypertension, type 2 diabetes mellitus, and coronary artery disease. Current medications include pravastatin, lisinopril, metformin, and aspirin. His temperature is 37°C (98.6°F), pulse is 76/min, and blood pressure is 165/90 mm Hg. He is right-handed. The patient speaks in short, simple sentences, and has difficulty repeating sequences of words. He can follow simple instructions. Right facial droop is present. Muscle strength is 4/5 on the right side and 5/5 on the left, and there is a mild right-sided pronator drift. Which of the following is the most likely cause of the patient's symptoms? Options: A. Occlusion of the right penetrating arteries B. Occlusion of the right middle cerebral artery C. Occlusion of the left middle cerebral artery D. Occlusion of the right posterior inferior cerebellar artery E. Rupture of left posterior cerebral artery malformation | E6: Answer: C Reasoning: The patient has acute onset right-sided weakness, right facial droop, and expressive (Broca's) aphasia, which localizes to the left (dominant) frontal lobe supplied by the left middle cerebral artery. Confidence: 100% | F6: Occlusion of the left middle cerebral artery (Answer Index: C) | G6: Yes | H6: 1 | I6: 1 | J6: 1 | K6: 1 | L6: 1 | M6: 1 | N6: 1 | O6: 1 | P6: =1-((ABS(H6-I6))+(ABS(J6-K6))+(ABS(L6-M6))+(ABS(N6-O6)))/4 -> 1 | W6: =(H6+J6+L6+N6)/4 -> 1 | X6: =(I6+K6+M6+O6)/4 -> 1
A7: CV_005 | B7: GPT-4 | C7: zero-shot | D7: A 48-year-old man comes to the physician because of worsening shortness of breath and nocturnal cough for the past 2 weeks. On two occasions, his cough was bloody. He had a heart condition as a child that was treated with antibiotics. He emigrated to the US from Kazakhstan 15 years ago. Pulmonary examination shows crackles at both lung bases. Cardiac examination is shown. Which of the following is the most likely diagnosis? Options: A. Aortic valve regurgitation B. Mitral valve prolapse C. Mitral valve stenosis D. Mitral valve regurgitation E. Tricuspid valve stenosis " | E7: Answer: C Reasoning: The patient's history of childhood heart condition treated with antibiotics (suggesting rheumatic fever), origin from an area with higher rheumatic heart disease prevalence, and symptoms of pulmonary congestion (dyspnea, nocturnal cough, hemoptysis, crackles) point to mitral valve stenosis. Confidence: 95% | F7: Mitral valve stenosis (Answer Index: C) | G7: Yes | H7: 1 | I7: 1 | J7: 1 | K7: 1 | L7: 1 | M7: 1 | N7: 1 | O7: 1 | P7: =1-((ABS(H7-I7))+(ABS(J7-K7))+(ABS(L7-M7))+(ABS(N7-O7)))/4 -> 1 | W7: =(H7+J7+L7+N7)/4 -> 1 | X7: =(I7+K7+M7+O7)/4 -> 1
A8: CV_006 | B8: GPT-4 | C8: zero-shot | D8: A 4-year-old boy is brought to the physician for a well-child examination. He started walking at 20 months of age. He can use a cup to drink but cannot use silverware. He speaks in 2-word sentences and can build a tower of 4 blocks. He can scribble but cannot draw a circle. He is above the 99th percentile for height and at the 15th percentile for weight. Vital signs are within normal limits. Examination shows bilateral inferior lens dislocation. His fingers are long and slender. He has a high-arched palate. The thumb and 5th finger overlap when he grips a wrist with the opposite hand. The skin over the neck can be extended and stretched easily. Which of the following is the most likely cause of these findings? Options: A. Hypoxanthine-guanine-phosphoribosyl transferase deficiency B. Fibrillin 1 deficiency C. Type V collagen deficiency D. Cystathionine synthase deficiency E. Galactokinase deficiency | E8: Answer: D Reasoning: The boy has developmental delay, tall stature, long fingers, lens dislocation (inferior), and hyperextensible skin, which are classic for homocystinuria due to cystathionine synthase deficiency. Confidence: 100% | F8: Cystathionine synthase deficiency (Answer Index: D) | G8: Yes | H8: 1 | I8: 1 | J8: 1 | K8: 1 | L8: 1 | M8: 1 | N8: 1 | O8: 1 | P8: =1-((ABS(H8-I8))+(ABS(J8-K8))+(ABS(L8-M8))+(ABS(N8-O8)))/4 -> 1 | W8: =(H8+J8+L8+N8)/4 -> 1 | X8: =(I8+K8+M8+O8)/4 -> 1
A9: CV_007 | B9: GPT-4 | C9: zero-shot | D9: A 4-year-old girl is brought to the physician with a 3-month history of progressive intermittent pain and swelling involving both knees, right ankle, and right wrist. The patient has been undergoing treatment with acetaminophen and ice packs, both of which relieved her symptoms. The affected joints feel "stuck” and are difficult to move immediately upon waking up in the morning. However, the patient can move her joints freely after a few minutes. She also complains of occasional mild eye pain that resolves spontaneously. Five months ago, she was diagnosed with an upper respiratory tract infection that resolved without treatment. Vital signs are within normal limits. Physical examination shows swollen and erythematous joints, which are tender to touch. Slit-lamp examination shows an anterior chamber flare with signs of iris inflammation bilaterally. Laboratory studies show: Blood parameters Hemoglobin 12.6 g/dL Leukocyte count 8,000/mm3 Segmented neutrophils 76% Eosinophils 1% Lymphocytes 20% Monocytes 3% Platelet count 360,000/mm3 Erythrocyte sedimentation rate 36 mm/hr Serum parameters Antinuclear antibodies 1:320 Rheumatoid factor negative Which of the following is the most likely diagnosis? Options: A. Acute lymphocytic leukemia B. Enthesitis-related arthritis C. Oligoarticular juvenile idiopathic arthritis D. Postinfectious arthritis E. Seronegative polyarticular juvenile idiopathic arthritis | E9: Answer: C Reasoning: The patient has a chronic, insidious onset of arthritis involving ≤4 joints (oligoarticular), morning stiffness, and uveitis, with positive ANA and negative RF, which is characteristic of oligoarticular juvenile idiopathic arthritis. Confidence: 100% | F9: Oligoarticular juvenile idiopathic arthritis (Answer Index: C) | G9: Yes | H9: 1 | I9: 1 | J9: 1 | K9: 1 | L9: 1 | M9: 1 | N9: 1 | O9: 1 | P9: =1-((ABS(H9-I9))+(ABS(J9-K9))+(ABS(L9-M9))+(ABS(N9-O9)))/4 -> 1 | W9: =(H9+J9+L9+N9)/4 -> 1 | X9: =(I9+K9+M9+O9)/4 -> 1
A10: CV_008 | B10: GPT-4 | C10: zero-shot | D10: A 35-year-old is brought into the emergency room after a bicycle vs motored vehicle accident. He was unconscious after hitting the side of his head on the road, but recovered consciousness after a few minutes. He started to ride his bicycle again, but then developed a severe headache with nausea and vomiting, at which time he called EMS. While in the hospital, the patient is confused and cannot provide a history. He quickly loses consciousness and his CT scan is displayed in Figure 1. What is the most likely diagnosis? Options: A. Subarachnoid hemorrhage B. Subdural hematoma C. Epidural hematoma D. Subgaleal hematoma E. Caput succedaneum | E10: Answer: C Reasoning: The classic presentation of loss of consciousness, a lucid interval, followed by rapid deterioration after head trauma is characteristic of an epidural hematoma, often due to middle meningeal artery injury. Confidence: 100% | F10: Epidural hematoma (Answer Index: C) | G10: Yes | H10: 1 | I10: 1 | J10: 1 | K10: 1 | L10: 1 | M10: 1 | N10: 1 | O10: 1 | P10: =1-((ABS(H10-I10))+(ABS(J10-K10))+(ABS(L10-M10))+(ABS(N10-O10)))/4 -> 1 | W10: =(H10+J10+L10+N10)/4 -> 1 | X10: =(I10+K10+M10+O10)/4 -> 1
A11: CV_009 | B11: GPT-4 | C11: zero-shot | D11: A 79-year-old man is admitted to the intensive care unit for hospital acquired pneumonia, a COPD flare, and acute heart failure requiring intubation and mechanical ventilation. On his first night in the intensive care unit, his temperature is 99.7°F (37.6°C), blood pressure is 107/58 mm Hg, and pulse is 150/min which is a sudden change from his previous vitals. Physical exam is notable for jugular venous distension and a rapid heart rate. The ventilator is checked and is functioning normally. Which of the following is the best next step in management for the most likely diagnosis? Options: A. Chest radiograph B. FAST exam C. Needle thoracostomy D. Thoracotomy E. Tube thoracostomy | E11: Answer: C Reasoning: The patient has sudden-onset tachycardia, hypotension, and jugular venous distension while on mechanical ventilation, suggesting tension pneumothorax, which requires immediate needle thoracostomy before confirmatory imaging. Confidence: 95% | F11: Needle thoracostomy (Answer Index: C) | G11: Yes | H11: 1 | I11: 1 | J11: 1 | K11: 1 | L11: 1 | M11: 1 | N11: 1 | O11: 1 | P11: =1-((ABS(H11-I11))+(ABS(J11-K11))+(ABS(L11-M11))+(ABS(N11-O11)))/4 -> 1 | W11: =(H11+J11+L11+N11)/4 -> 1 | X11: =(I11+K11+M11+O11)/4 -> 1
A12: CV_010 | B12: GPT-4 | C12: zero-shot | D12: A primigravida, 29-year-old woman presents in her 28th week of pregnancy for evaluation of 3 hours of vaginal bleeding and abdominal pain. She denies any trauma and states that this is the first time she has had such symptoms. Her prenatal care has been optimal and all of her antenatal screenings have been within normal limits. Her vital signs are unremarkable. Physical examination reveals a small amount of blood in the vaginal canal and the cervical os is closed. Ultrasound imaging demonstrates positive fetal cardiac activity. What is the most likely diagnosis? Options: A. Complete abortion B. Incomplete abortion C. Inevitable abortion D. Missed abortion E. Threatened abortion | E12: Answer: E Reasoning: The patient has vaginal bleeding and abdominal pain in the second trimester, but the cervical os is closed and fetal cardiac activity is present, which is consistent with a threatened abortion. Confidence: 100% | F12: Threatened abortion (Answer Index: E) | G12: Yes | H12: 1 | I12: 1 | J12: 1 | K12: 1 | L12: 1 | M12: 1 | N12: 1 | O12: 1 | P12: =1-((ABS(H12-I12))+(ABS(J12-K12))+(ABS(L12-M12))+(ABS(N12-O12)))/4 -> 1 | W12: =(H12+J12+L12+N12)/4 -> 1 | X12: =(I12+K12+M12+O12)/4 -> 1
A13: CV_011 | B13: GPT-4 | C13: zero-shot | D13: A 34-year-old woman comes to the emergency department because of right flank pain and vomiting for 5 hours. She has had fever and chills for the past 2 days. She attended a barbecue 3 days ago, where she ate egg salad. She underwent surgery for left ovarian torsion a year ago. Menses occur at regular 28-day intervals and last 5 days. She is sexually active with 2 male partners and uses condoms inconsistently. Her only medication is an oral contraceptive pill. She is 163 cm (5 ft 4 in) tall and weighs 72.5 kg (160 lb); BMI is 27.5 kg/m2. She appears uncomfortable. Her temperature is 38.9°C (102°F), pulse is 101/min, and blood pressure is 118/76 mm Hg. The lungs are clear to auscultation. The right lower quadrant and right flank show severe tenderness to palpation. Pelvic examination shows no abnormalities. Laboratory studies show: Hemoglobin 12.8 g/dL Leukocyte count 14,200/mm3 Platelet count 230,000/mm3 Serum Na+ 136 mEq/L K+ 3.8 mEq/L Cl- 103 mEq/L Urea nitrogen 23 mg/dL Creatinine 1.2 mg/dL Urine Blood 1+ Protein 1+ Glucose negative Leukocyte esterase positive Nitrites negative RBC 6–8/hpf WBC 80–85/hpf Which of the following is the most likely diagnosis?" Options: A. Ovarian torsion B. Gastroenteritis C. Urethritis D. Pelvic inflammatory disease E. Pyelonephritis | E13: Answer: E Reasoning: The patient has fever, chills, right flank pain, vomiting, leukocytosis, and urinalysis showing pyuria and hematuria, which are most consistent with pyelonephritis. Confidence: 100% | F13: Pyelonephritis (Answer Index: E) | G13: Yes | H13: 1 | I13: 1 | J13: 0.5 | K13: 1 | L13: 1 | M13: 1 | N13: 1 | O13: 1 | P13: =1-((ABS(H13-I13))+(ABS(J13-K13))+(ABS(L13-M13))+(ABS(N13-O13)))/4 -> 0.875 | W13: =(H13+J13+L13+N13)/4 -> 0.875 | X13: =(I13+K13+M13+O13)/4 -> 1
A14: CV_012 | B14: GPT-4 | C14: zero-shot | D14: A 47-year-old woman presents with intermittent throbbing headaches. She says that she has had at least 1–2 every week for the last 3 months. She describes the pain as severe, pulsatile, and localized to the right frontotemporal and periorbital areas. She says the headaches usually last for several hours and are made worse by the presence of light. She endorses nausea with occasional vomiting during the most severe episodes. She denies any seizures, loss of consciousness, or focal neurologic deficits. Her past medical history is significant for myocardial infarction (MI) 1 year ago, status post percutaneous transluminal coronary angioplasty complicated by residual angina, and severe asthma, managed medically. The patient is afebrile, and the vital signs are within normal limits. A physical examination is unremarkable. A noncontrast computed tomography (CT) scan of the head appears normal. Which of the following is the best prophylactic treatment for this patient’s most likely diagnosis? Options: A. Sumatriptan B. Amitriptyline C. Valproic acid D. Propranolol E. Ibuprofen | E14: Answer: B Reasoning: Amitriptyline is an effective prophylactic agent for migraine and is preferred in patients with contraindications to beta-blockers (propranolol) and valproic acid, such as those with a history of MI and severe asthma. Confidence: 95% | F14: Valproic acid (Answer Index: C) | G14: No | H14: 1 | I14: 1 | J14: 1 | K14: 1 | L14: 0 | M14: 0 | N14: 1 | O14: 1 | P14: =1-((ABS(H14-I14))+(ABS(J14-K14))+(ABS(L14-M14))+(ABS(N14-O14)))/4 -> 1 | W14: =(H14+J14+L14+N14)/4 -> 0.75 | X14: =(I14+K14+M14+O14)/4 -> 0.75
A15: CV_013 | B15: GPT-4 | C15: zero-shot | D15: A 51-year-old woman presents the following significant and unintentional weight loss. She denies any personal history of blood clots in her past, but she says that her mother has also had to be treated for pulmonary embolism in the recent past. She also mentions that she had been struggling with her weight, so she was initially content with losing the weight, but her daughter convinced her to come to the office to be checked out. Her past medical history is significant for preeclampsia, hypertension, polycystic ovarian syndrome, and hypercholesterolemia. She currently smokes 1 pack of cigarettes per day, drinks a glass of wine per day, and she currently denies any illicit drug use, although she has a remote past of injection drug use with heroin. The vital signs include: temperature 36.7°C (98.0°F), blood pressure 126/74 mm Hg, heart rate 111/min and irregular, and respiratory rate 17/min. On physical examination, her pulses are bounding and complexion is pale, but breath sounds remain clear. Oxygen saturation was initially 91% on room air and electrocardiogram (ECG) showed atrial fibrillation. Upon further discussion with the patient, her physician discovers that she is having some cognitive difficulty. Her leukocyte count is elevated to 128,000/mm3, and she has elevated lactate dehydrogenase (LDH), uric acid, and B-12 levels. A BCR-ABL translocation is present, as evidenced by the Philadelphia chromosome. What is the most likely diagnosis for this patient? Options: A. Acute lymphocytic leukemia B. Acute myelogenous leukemia C. Chronic lymphocytic leukemia D. Chronic myelogenous leukemia E. Hairy cell leukemia | E15: Answer: D Reasoning: The presence of a markedly elevated leukocyte count, elevated LDH, uric acid, B-12, and especially the BCR-ABL translocation (Philadelphia chromosome) is diagnostic for chronic myelogenous leukemia (CML). Confidence: 100% | F15: Chronic myelogenous leukemia (Answer Index: D) | G15: Yes | H15: 1 | I15: 1 | J15: 1 | K15: 1 | L15: 1 | M15: 1 | N15: 1 | O15: 1 | P15: =1-((ABS(H15-I15))+(ABS(J15-K15))+(ABS(L15-M15))+(ABS(N15-O15)))/4 -> 1 | W15: =(H15+J15+L15+N15)/4 -> 1 | X15: =(I15+K15+M15+O15)/4 -> 1
A16: CV_014 | B16: GPT-4 | C16: zero-shot | D16: A 32-year-old G0P0 female complains of unsuccessful pregnancy since discontinuing an oral contraceptive 12 months ago. She reports menarche at age 15 and has had irregular periods since. She had occasional spotting while taking an oral contraceptive, but she has not had a “normal period” since discontinuing the pill. She currently denies having any hot flashes. Physical examination reveals normal height and BMI. A speculum examination shows atrophic vagina. Thyroid-stimulating hormone and prolactin concentrations are within normal limits. The patient tests negative for a qualitative serum beta‐hCG. The laboratory findings include a follicle-stimulating hormone (FSH) level of 56 mIU/mL and an estradiol level of <18 pmol/L, confirmed by 2 separate readings within 2 months. Based on her history, physical examination, and laboratory findings, what is the most likely cause of her infertility? Options: A. Polycystic ovary syndrome B. Hyperprolactinemia C. Primary ovarian insufficiency D. Secondary ovarian insufficiency E. Menopause | E16: Answer: C Reasoning: The patient is a young woman with infertility, irregular menses, atrophic vagina, elevated FSH, and low estradiol, all consistent with primary ovarian insufficiency. Confidence: 100% | F16: Primary ovarian insufficiency (Answer Index: C) | G16: Yes | H16: 1 | I16: 1 | J16: 1 | K16: 1 | L16: 1 | M16: 1 | N16: 1 | O16: 1 | P16: =1-((ABS(H16-I16))+(ABS(J16-K16))+(ABS(L16-M16))+(ABS(N16-O16)))/4 -> 1 | W16: =(H16+J16+L16+N16)/4 -> 1 | X16: =(I16+K16+M16+O16)/4 -> 1
A17: CV_015 | B17: GPT-4 | C17: zero-shot | D17: A 34-year-old African-American woman comes to the physician because of a 6-month history of fatigue, increasing shortness of breath on exertion, and a dry cough. She also has chronic constipation with bowel movements once every two to three days. She has not had fevers, night sweats, or weight loss. She has a history of hypertension and arthritis of both ankle joints. Current medications include hydrochlorothiazide and daily multivitamins. Her vital signs are within normal limits. Her serum sodium is 138 mEq/L, potassium is 3.9 mEq/L, and calcium is 11.5 mg/dL. An x-ray of the chest shows bilateral hilar lymphadenopathy and normal lung parenchyma. Which of the following is the most likely cause of this patient's hypercalcemia? Options: A. Elevated 1,25-dihydroxyvitamin D3 levels B. PTH-related protein production C. Thiazide-induced renal calcium reabsorption D. Chronic kidney disease E. Vitamin A toxicity " | E17: Answer: A Reasoning: The patient's presentation is most consistent with sarcoidosis, which can cause hypercalcemia due to increased production of 1,25-dihydroxyvitamin D3 by activated macrophages in granulomas. Confidence: 100% | F17: Elevated 1,25-dihydroxyvitamin D3 levels (Answer Index: A) | G17: Yes | H17: 1 | I17: 1 | J17: 0.5 | K17: 1 | L17: 1 | M17: 1 | N17: 1 | O17: 1 | P17: =1-((ABS(H17-I17))+(ABS(J17-K17))+(ABS(L17-M17))+(ABS(N17-O17)))/4 -> 0.875 | W17: =(H17+J17+L17+N17)/4 -> 0.875 | X17: =(I17+K17+M17+O17)/4 -> 1
... A152: CV_050 | B152: GPT-4 | C152: chain-of-thought | D152: A 2-month-old infant is brought in by his mother for runny nose and cough. She reports he had an ear infection 2 weeks ago, and since then he has had a productive cough and nasal congestion. His medical history is significant for multiple ear infections and eczematous dermatitis. He has also been hospitalized for 2 episodes of severe viral bronchiolitis. The mother reports that the infant has a good appetite but has had intermittent, non-bloody diarrhea. The patient is at the 20th percentile for weight. On physical examination, the patient has widespread, dry, erythematous patches, mucopurulent nasal drip, and crusting of the nares. His tongue is coated by a thick white film which is easily scraped off. Crackles are heard at the left lung base. Labs are drawn, as shown below: Hemoglobin: 12.8 g/dL Platelets: 280,000/mm^3 Leukocytes: 7,500/mm^3 Neutrophils: 5,500/mm^3 Lymphocytes: 2,000/mm^3 Serum: Na+: 138 mEq/L Cl-: 96 mEq/L K+: 4.3 mEq/L HCO3-: 23 mEq/L Urea nitrogen: 18 mg/dL Glucose: 90 mg/dL Creatinine: 1.0 mg/dL Ca2+: : 9.2 mg/dL Which of the following is the most likely cause of this patient’s presentation? Options: A. 22q11.2 deletion B. Adenosine deaminase deficiency C. Defective leukocyte adhesion D. Defective tyrosine kinase E. WAS gene mutation | E152: Reasoning: This 2-month-old has recurrent ear infections, severe viral bronchiolitis, persistent productive cough, eczema, oral thrush, and intermittent diarrhea. Labs show normal neutrophils and lymphocytes, and no cytopenias. The combination of recurrent sinopulmonary and ear infections, eczema, and thrush suggests an immunodeficiency. The most likely is X-linked (Bruton) agammaglobulinemia (defective tyrosine kinase), but this typically presents after 6 months, and with absent lymphocytes. Wiskott-Aldrich syndrome (WAS gene mutation) presents with eczema, recurrent infections, and thrombocytopenia (not seen here). 22q11.2 deletion (DiGeorge) would have lymphopenia and hypocalcemia. Adenosine deaminase deficiency (SCID) would have severe lymphopenia and more severe infections. Defective leukocyte adhesion presents with delayed umbilical cord separation and poor wound healing, not this pattern. The best fit is defective tyrosine kinase (Bruton agammaglobulinemia), as the child has recurrent bacterial infections, eczema, and normal lymphocyte count (early in disease, before maternal IgG wanes). Answer: D Confidence: 85% | F152: Adenosine deaminase deficiency (Answer Index: B) | G152: No | H152: 0.5 | I152: 0.5 | J152: 1 | K152: 1 | L152: 0 | M152: 0 | N152: 0.5 | O152: 0.5 | P152: =1-((ABS(H152-I152))+(ABS(J152-K152))+(ABS(L152-M152))+(ABS(N152-O152)))/4 -> 1 | W152: =(H152+J152+L152+N152)/4 -> 0.5 | X152: =(I152+K152+M152+O152)/4 -> 0.5

Sheet Claude
A1: LLM Clinical Vignette Evaluations | H1: Plausibility (0/0.5/1) | J1: Faithfulness (0/0.5/1) | L1: Calibration (0/0.5/1) | N1: Harmfulness (0/0.5/1) | Q1: Average Accuracy
A2: Case ID (This matches to the IDs in .json dataset) | B2: Model | C2: Prompt Type | D2: Vignette | E2: Text Output (Model Response) | F2: Correct Diagnosis | G2: Correct Diagnosis? (Y/N) | H2: Human Evaluation | I2: Model Self-Score | J2: Human Evaluation | K2: Model Self-Score | L2: Human Evaluation | M2: Model Self-Score | N2: Human Evaluation | O2: Model Self-Score | P2: Accuracy Score | Q2: Zero-shot | R2: Few-shot | S2: Chain-of-Thought | U2: Average Human Score | V2: Average Self Score | X2: Average Human Score (0) | Y2: Average Self Score (0) | Z2: Average Human Score (F) | AA2: Average Self Score (F) | AB2: Average Human Score (C) | AC2: Average Self Score (C)
A3: CV_001 | B3: Claude Opus | C3: zero-shot | D3: A 9-year-old girl is brought to the pediatrician for a wellness checkup. The girl's past medical history is non-contributory, and she has met all her developmental milestones. Her parents were recently called into the office as the girl was found touching the genitals of one of her classmates. She was trying to insert a toy into her classmate's genitals. The girl is asked what has happened and what she thinks is going on but she is too shy to reply to the physician. The girl and her mother recently moved in with a family member. They live in low-income housing subsidized by the government and are currently on food stamps. The mother states that her daughter has been particularly argumentative lately and that they have gotten into arguments in which her daughter screamed at her and locked herself in the bathroom. Which of the following is the most likely diagnosis? | E3: Answer: E Reasoning: The child's sexualized behavior (touching classmate's genitals, attempting penetration with a toy) is age-inappropriate and highly concerning for sexual abuse. This is particularly significant given the recent move to live with a family member, creating a new exposure risk. While increased conflict with parents can occur normally, the combination of inappropriate sexual knowledge/behavior in a 9-year-old is a red flag requiring immediate investigation for abuse. Confidence: 95% | F3: Left ventricular free wall rupture | G3: Yes | H3: 0 | I3: 1 | J3: 1 | K3: 1 | L3: 1 | M3: 1 | N3: 0.5 | O3: 1 | P3: =1-((ABS(H3-I3))+(ABS(J3-K3))+(ABS(L3-M3))+(ABS(N3-O3)))/4 -> 0.625 | Q3: =AVERAGE(P3:P52) -> 0.805 | R3: =AVERAGE(P53:P102) -> 0.785 | S3: =AVERAGE(P103:P152) -> 0.9875 | U3: =(H3+J3+L3+N3)/4 -> 0.625 | V3: =(I3+K3+M3+O3)/4 -> 1 | X3: =AVERAGE(U3:U52) -> 0.81 | Y3: =AVERAGE(V3:V52) -> 0.98 | Z3: =AVERAGE(U53:U102) -> 0.7875 | AA3: =AVERAGE(V53:V102) -> 0.9675 | AB3: =AVERAGE(U103:U152) -> 0.9725 | AC3: =AVERAGE(V103:V152) -> 0.98
A4: CV_002 | B4: Claude Opus | C4: zero-shot | D4: An obese 50-year-old woman presents to the emergency department of a rural hospital due to chest pain for the last 12 hours. The pain is substernal, crushing in nature, radiating into her neck, and accompanied by profuse sweating. Her history is significant for hypertension, and she admits poor compliance with her medications. An ECG done at the clinic confirmed the presence of STEMI, and the patient was given aspirin. The ambulance was in an accident on the way to the hospital and by the time the patient reached the angiography suite, the cardiologist decided intervention should be delayed due to the late presentation. Also, the patient’s pain has improved. The patient is admitted and is stable for 3 nights with no dyspnea or edema. Her blood pressure is kept under control while in the hospital. On the fourth night, the patient becomes quite agitated and soon thereafter she is unresponsive. Her pulse cannot be palpated. She has an elevated JVP and upon auscultation, heart sounds are distant. What is the most likely diagnosis for this patient? | E4: Answer: C Reasoning: The patient presents with a late complication of STEMI (day 4 post-infarction). The sudden deterioration with elevated JVP, distant heart sounds, and pulselessness suggests cardiac tamponade from left ventricular free wall rupture. This typically occurs 3-5 days post-MI when the necrotic myocardium is weakest, leading to hemopericardium and obstructive shock. Confidence: 95% | F4: Prenatal alcohol exposure | G4: Yes | H4: 1 | I4: 1 | J4: 1 | K4: 1 | L4: 1 | M4: 1 | N4: 1 | O4: 1 | P4: =1-((ABS(H4-I4))+(ABS(J4-K4))+(ABS(L4-M4))+(ABS(N4-O4)))/4 -> 1 | U4: =(H4+J4+L4+N4)/4 -> 1 | V4: =(I4+K4+M4+O4)/4 -> 1
A5: CV_003 | B5: Claude Opus | C5: zero-shot | D5: A 6-year-old boy is brought to the physician because of inability to concentrate and difficulties completing assignments at school. His mother says that he frequently interrupts others during conversations at home and that his teachers often reprimand him for talking excessively in school. He refuses to play with the other children and often has physical altercations with his classmates. He can jump up and down but he cannot hop on one foot. He eats without assistance but has difficulty using silverware. He cannot follow three-step directions. There is no family history of serious illness. Examination shows a small head, wide-spaced eyes, and short palpebral fissures. His upper lip is thin and flat. He has a sunken nasal bridge and a small jaw. There is a 3/6 pansystolic murmur heard along the left lower sternal border. Which of the following is the most likely cause of these findings? | E5: Answer: C Reasoning: The clinical presentation includes characteristic facial features (thin upper lip, smooth philtrum, short palpebral fissures, small jaw, sunken nasal bridge), microcephaly, cardiac defect (VSD suggested by pansystolic murmur), developmental delays, behavioral problems, and fine motor difficulties. This constellation is classic for fetal alcohol syndrome (FAS), caused by prenatal alcohol exposure. Confidence: 95% | F5: Acute mesenteric ischemia | G5: Yes | H5: 1 | I5: 1 | J5: 1 | K5: 1 | L5: 0.5 | M5: 1 | N5: 1 | O5: 1 | P5: =1-((ABS(H5-I5))+(ABS(J5-K5))+(ABS(L5-M5))+(ABS(N5-O5)))/4 -> 0.875 | U5: =(H5+J5+L5+N5)/4 -> 0.875 | V5: =(I5+K5+M5+O5)/4 -> 1
A6: CV_004 | B6: Claude Opus | C6: zero-shot | D6: A 57-year-old man presents with 2 days of severe, generalized, abdominal pain that is worse after meals. He is also nauseated and reports occasional diarrhea mixed with blood. Apart from essential hypertension, his medical history is unremarkable. His vital signs include a temperature of 36.9°C (98.4°F), blood pressure of 145/92 mm Hg, and an irregularly irregular pulse of 105/min. Physical examination is only notable for mild periumbilical tenderness. Which of the following is the most likely diagnosis? | E6: Answer: C Reasoning: The key features are an irregularly irregular pulse (atrial fibrillation), severe abdominal pain out of proportion to physical exam findings (mild periumbilical tenderness), and bloody diarrhea in an older patient. This classic triad strongly suggests acute mesenteric ischemia, likely from an embolic event secondary to atrial fibrillation. Confidence: 95% | F6: Cyclic vomiting syndrome | G6: Yes | H6: 1 | I6: 1 | J6: 1 | K6: 1 | L6: 1 | M6: 1 | N6: 0.5 | O6: 1 | P6: =1-((ABS(H6-I6))+(ABS(J6-K6))+(ABS(L6-M6))+(ABS(N6-O6)))/4 -> 0.875 | U6: =(H6+J6+L6+N6)/4 -> 0.875 | V6: =(I6+K6+M6+O6)/4 -> 1
A7: CV_005 | B7: Claude Opus | C7: zero-shot | D7: A 5-year-old male is brought to the pediatrician by his mother, who relates a primary complaint of a recent history of five independent episodes of vomiting over the last 10 months, most recently 3 weeks ago. Each time, he has awoken early in the morning appearing pale, feverish, lethargic, and complaining of severe nausea. This is followed by 8-12 episodes of non-bilious vomiting over the next 24 hours. Between these episodes he returns to normal activity. He has no significant past medical history and takes no other medications. Review of systems is negative for changes in vision, gait disturbance, or blood in his stool. His family history is significant only for migraine headaches. Vital signs and physical examination are within normal limits. Initial complete blood count, comprehensive metabolic panel, and abdominal radiograph were unremarkable. What is the most likely diagnosis? | E7: Answer: C Reasoning: This child presents with stereotypical recurrent episodes of severe vomiting separated by symptom-free intervals, occurring early morning with associated symptoms (pallor, lethargy, nausea), lasting ~24 hours, with complete return to baseline between episodes. The family history of migraines and negative workup strongly support cyclic vomiting syndrome, which is associated with migraine disorders. Confidence: 95% | F7: Acute gout | G7: Yes | H7: 1 | I7: 1 | J7: 1 | K7: 1 | L7: 1 | M7: 1 | N7: 1 | O7: 1 | P7: =1-((ABS(H7-I7))+(ABS(J7-K7))+(ABS(L7-M7))+(ABS(N7-O7)))/4 -> 1 | U7: =(H7+J7+L7+N7)/4 -> 1 | V7: =(I7+K7+M7+O7)/4 -> 1
A8: CV_006 | B8: Claude Opus | C8: zero-shot | D8: A 45-year-old man comes to the emergency department with the complaint of pain and swelling of the proximal joint in the third finger of his right hand. The pain is so severe that it woke him up from sleep this morning. He has never had an episode like this before. The patient has smoked a pack of cigarettes daily for the last 25 years and drinks alcohol heavily each weekend. His friend threw a party last night where he drank 3–4 beers and was unable to drive back home. He has no past medical illness. His mother died of pancreatic cancer at age 55, and his father died of a stroke 2 years ago. His temperature is 37.7°C (100°F), blood pressure is 130/70 mm Hg, pulse is 104/min, respiratory rate is 20/min, and BMI is 25 kg/m2. The patient is in moderate distress due to the pain. On examination, the proximal interphalangeal joint of the third finger of his right hand is very tender to touch, swollen, warm, and slightly red in color. Range of motion cannot be assessed due to extreme tenderness. The patient’s right hand is shown in the image. Laboratory investigation Complete blood count: Hemoglobin 14.5 g/dL Leukocytes 16,000/mm3 Platelets 150,000/mm3 ESR 55mm/hr Synovial fluid is aspirated from the joint. The findings are: Appearance Cloudy, dense yellow WBC 30,000 cells/µL Culture Negative Negatively birefringent needle-shaped crystals are seen. Which of the following is the most likely diagnosis? | E8: Answer: D Reasoning: The patient presents with acute monoarticular arthritis of a PIP joint with synovial fluid showing negatively birefringent needle-shaped crystals, which are pathognomonic for monosodium urate crystals in gout. The acute onset, severe pain waking him from sleep, and recent alcohol consumption (a known trigger) are classic for an acute gout attack. While the PIP joint is less commonly affected than the first MTP joint, it can still be involved in acute gout. Confidence: 95% | F8: Crohn disease | G8: Yes | H8: 1 | I8: 1 | J8: 1 | K8: 1 | L8: 0 | M8: 1 | N8: 0.5 | O8: 1 | P8: =1-((ABS(H8-I8))+(ABS(J8-K8))+(ABS(L8-M8))+(ABS(N8-O8)))/4 -> 0.625 | U8: =(H8+J8+L8+N8)/4 -> 0.625 | V8: =(I8+K8+M8+O8)/4 -> 1
A9: CV_007 | B9: Claude Opus | C9: zero-shot | D9: A 61-year-old man comes to the physician because of fatigue, diarrhea, and crampy abdominal pain for 3 weeks. The abdominal pain is worse after eating. During the past week, he has had up to 4 watery stools daily. He has also had pain in his mouth and gums for 6 days. He has not had nausea, vomiting, or fever. Four months ago, he went on a 1-week trip to the Dominican Republic. He has atrial fibrillation, hypertension, and hypothyroidism. Current medications include levothyroxine, metoprolol, and warfarin. He has smoked one pack of cigarettes daily for 40 years. His temperature is 37.9°C (100.2°F), pulse is 81/min, and blood pressure is 120/75 mm Hg. Examination shows two 1-cm, tender ulcerative lesions in the mouth. Abdominal examination shows mild tenderness to palpation in the right lower quadrant without guarding or rebound. Bowel sounds are normal. His hemoglobin concentration is 11.5 g/dL, mean corpuscular volume is 77 fL, leukocyte count is 11,800 mm3, and platelet count is 360,000 mm3. Colonoscopy with biopsy of the colonic mucosa is performed. Analysis of the specimen shows non-caseating granulomas and neutrophilic inflammation of the crypts. Which of the following is the most likely diagnosis? | E9: Answer: C Reasoning: The patient presents with chronic diarrhea, abdominal pain, oral ulcers, and colonoscopy findings of non-caseating granulomas and crypt abscesses (neutrophilic inflammation of crypts). These findings are pathognomonic for Crohn disease. The microcytic anemia (MCV 77 fL) suggests chronic blood loss or malabsorption. While the travel history might suggest an infectious cause, the chronic course and histopathologic findings are classic for Crohn disease. Confidence: 95% | F9: Damage to the right superior gluteal nerve | G9: Yes | H9: 1 | I9: 1 | J9: 1 | K9: 1 | L9: 0 | M9: 1 | N9: 1 | O9: 1 | P9: =1-((ABS(H9-I9))+(ABS(J9-K9))+(ABS(L9-M9))+(ABS(N9-O9)))/4 -> 0.75 | U9: =(H9+J9+L9+N9)/4 -> 0.75 | V9: =(I9+K9+M9+O9)/4 -> 1
A10: CV_008 | B10: Claude Opus | C10: zero-shot | D10: A 6-year-old boy is brought to the physician because he has a limp for 3 weeks. He was born at term and has been healthy since. His immunization are up-to-date; he received his 5th DTaP vaccine one month ago. He is at 50th percentile for height and weight. His temperature is 37°C (98.6°F), pulse is 80/min and respirations are 28/min. When asked to stand only on his right leg, the left pelvis sags. The remainder of the examination shows no abnormalities. Which of the following is the most likely cause of these findings? | E10: Answer: E Reasoning: The positive Trendelenburg sign (left pelvis sags when standing on right leg) indicates weakness of the right hip abductors (gluteus medius and minimus), which are innervated by the superior gluteal nerve. The nerve supplying the stance leg is affected—when standing on the right leg, the right hip abductors cannot stabilize the pelvis, causing the contralateral (left) side to drop. Confidence: 95% | F10: Parvovirus infection | G10: Yes | H10: 0.5 | I10: 1 | J10: 1 | K10: 1 | L10: 0.5 | M10: 1 | N10: 0.5 | O10: 1 | P10: =1-((ABS(H10-I10))+(ABS(J10-K10))+(ABS(L10-M10))+(ABS(N10-O10)))/4 -> 0.625 | U10: =(H10+J10+L10+N10)/4 -> 0.625 | V10: =(I10+K10+M10+O10)/4 -> 1
A11: CV_009 | B11: Claude Opus | C11: zero-shot | D11: A 3-year-old boy presents with fever, generalized fatigue, nausea, and progressive anemia. The patient’s mother says his condition was normal until one week ago when he started having flu-like symptoms such as fever, general fatigue, and abdominal discomfort. Past medical experience is significant for sickle cell disease, diagnosed 2 years ago. His vital signs include: blood pressure 98/50 mm Hg, pulse 120/min, temperature 39.0℃ (102.0℉). On physical examination, the patient is crying excessively and his skin and the conjunctivae look pale. Splenomegaly is noted. There is no skin rash nor lymphadenopathy. Laboratory findings are significant for the following: Total WBC count 22,000/mm3 Neutrophils 35% Lymphocytes 44% Atypical lymphocytes 9% Monocytes 12% RBC 1. 6 million/mm3 Hb 5.4 g/dL Hct 14.4% MCV 86 fL MCHC 37.5% Reticulocytes 0.1% A peripheral blood smear shows sickle cells. A direct and indirect Coombs test is negative. Which of the following is the most likely cause of this patient’s most recent symptoms? | E11: Answer: A Reasoning: This sickle cell patient presents with severe anemia (Hb 5.4 g/dL), markedly low reticulocytes (0.1%), and flu-like prodrome. The combination of sudden worsening anemia with reticulocytopenia in a sickle cell patient is classic for aplastic crisis caused by parvovirus B19 infection, which temporarily halts red cell production. The negative Coombs test excludes hemolytic anemia (option B). Confidence: 98% | F11: Eosinophilic granulomatosis with polyangiitis " | G11: Yes | H11: 1 | I11: 1 | J11: 1 | K11: 1 | L11: 0 | M11: 1 | N11: 0.5 | O11: 1 | P11: =1-((ABS(H11-I11))+(ABS(J11-K11))+(ABS(L11-M11))+(ABS(N11-O11)))/4 -> 0.625 | U11: =(H11+J11+L11+N11)/4 -> 0.625 | V11: =(I11+K11+M11+O11)/4 -> 1
A12: CV_010 | B12: Claude Opus | C12: zero-shot | D12: A 40-year-old woman comes to the emergency department because of difficulty walking for the past 4 hours. She first noticed her symptoms after getting up this morning and her foot dragging while walking. She feels tired. She has a history of chronic sinusitis. Six months ago, she was diagnosed with asthma. Current medications include an albuterol inhaler and inhaled corticosteroids. Her temperature is 38.9°C (102°F), pulse is 80/min, and her blood pressure is 140/90 mm Hg. Auscultation of her lungs shows diffuse wheezing over bilateral lung fields. Physical examination shows tender subcutaneous nodules on the extensor surfaces of the elbows. There are palpable, non-blanching erythematous lesions on both shins. Dorsiflexion of the right foot is impaired. Sensation to pinprick, light touch, and vibration is decreased over the ulnar aspect of the left forearm. Laboratory studies show: Hemoglobin 11.3 g/dL Leukocyte count 24,500 Segmented neutrophils 48% Eosinophils 29% Lymphocytes 19% Monocytes 4% Platelet count 290,000/mm3 Serum Urea nitrogen 32 mg/dL Creatinine 1.85 mg/dL Urine Blood 2+ Protein 3+ Which of the following is the most likely diagnosis in this patient?" | E12: Answer: E Reasoning: This patient presents with asthma, chronic sinusitis, eosinophilia (29%), mononeuritis multiplex (foot drop and ulnar nerve involvement), palpable purpura, subcutaneous nodules, and renal involvement (elevated creatinine, hematuria, proteinuria). This constellation of findings is classic for eosinophilic granulomatosis with polyangiitis (Churg-Strauss syndrome), which characteristically affects patients with asthma and presents with peripheral eosinophilia and vasculitic manifestations. Confidence: 95% | F12: Open-angle glaucoma | G12: Yes | H12: 1 | I12: 1 | J12: 1 | K12: 1 | L12: 1 | M12: 1 | N12: 1 | O12: 1 | P12: =1-((ABS(H12-I12))+(ABS(J12-K12))+(ABS(L12-M12))+(ABS(N12-O12)))/4 -> 1 | U12: =(H12+J12+L12+N12)/4 -> 1 | V12: =(I12+K12+M12+O12)/4 -> 1
A13: CV_011 | B13: Claude Opus | C13: zero-shot | D13: A 64-year-old woman comes to the physician for a follow-up examination. She has had difficulty reading for the past 6 months. She tried using multiple over-the-counter glasses with different strengths, but they have not helped. She has hypertension and type 2 diabetes mellitus. Current medications include insulin and enalapril. Her temperature is 37.1°C (98.8°F), pulse is 80/min, and blood pressure is 126/84 mm Hg. The pupils are round and react sluggishly to light. Visual acuity in the left eye is 6/60 and in the right eye counting fingers at 6 feet. Fundoscopy shows pallor of the optic disc bilaterally. The cup-to-disk ratio is 0.7 in the left eye and 0.9 in the right eye (N = 0.3). Which of the following is the most likely diagnosis? | E13: Answer: D Reasoning: The key findings are optic disc pallor with increased cup-to-disc ratios (0.7 and 0.9 vs normal 0.3), sluggish pupillary reactions, and progressive visual loss not corrected by glasses. These findings indicate optic nerve damage with cupping characteristic of glaucoma. The chronic progressive nature and bilateral involvement with increased cup-to-disc ratio point to open-angle glaucoma rather than other options. Confidence: 92% | F13: Renal cell carcinoma | G13: Yes | H13: 1 | I13: 1 | J13: 1 | K13: 1 | L13: 1 | M13: 1 | N13: 1 | O13: 1 | P13: =1-((ABS(H13-I13))+(ABS(J13-K13))+(ABS(L13-M13))+(ABS(N13-O13)))/4 -> 1 | U13: =(H13+J13+L13+N13)/4 -> 1 | V13: =(I13+K13+M13+O13)/4 -> 1
A14: CV_012 | B14: Claude Opus | C14: zero-shot | D14: A 53-year-old male presents to your office for abdominal discomfort. The patient states he first noticed pain on his right flank several months ago, and it has been gradually getting worse. For the past week, he has also noticed blood in his urine. Prior to this episode, he has been healthy and does not take any medications. The patient denies fever, chills, and dysuria. He has a 40 pack-year smoking history. Vital signs are T 37 C, HR 140/90 mmHg, HR 84/min, RR 14/min, O2 98%. Physical exam is unremarkable. CBC reveals a hemoglobin of 17 and hematocrit of 51%, and urinalysis is positive for red blood cells, negative for leukocytes. Which of the following is the most likely diagnosis? | E14: Answer: A Reasoning: The patient presents with a classic triad suggestive of renal cell carcinoma: flank pain, hematuria, and a parenchymal renal mass. Additionally, he has polycythemia (elevated hemoglobin/hematocrit), which can occur in RCC due to paraneoplastic erythropoietin production. His significant smoking history is a risk factor. The absence of infection signs rules out pyelonephritis, and the presentation doesn't fit polycystic kidney disease or AAA. Confidence: 95% | F14: Cellulitis | G14: Yes | H14: 1 | I14: 1 | J14: 1 | K14: 1 | L14: 0 | M14: 1 | N14: 0.5 | O14: 1 | P14: =1-((ABS(H14-I14))+(ABS(J14-K14))+(ABS(L14-M14))+(ABS(N14-O14)))/4 -> 0.625 | U14: =(H14+J14+L14+N14)/4 -> 0.625 | V14: =(I14+K14+M14+O14)/4 -> 1
A15: CV_013 | B15: Claude Opus | C15: zero-shot | D15: A 74-year-old woman presents to the clinic for evaluation of an erythematous and edematous skin rash on her right leg that has progressively worsened over the last 2 weeks. The medical history is significant for hypertension and diabetes mellitus type 2. She takes prescribed lisinopril and metformin. The vital signs include: blood pressure 152/92 mm Hg, heart rate 76/min, respiratory rate 12/min, and temperature 37.8°C (100.1°F). On physical exam, the patient appears alert and oriented. Observation of the lesion reveals a poorly demarcated region of erythema and edema along the anterior aspect of the right tibia. Within the region of erythema is a 2–3 millimeter linear break in the skin that does not reveal any serous or purulent discharge. Tenderness to palpation and warmth is associated with the lesion. There are no vesicles, pustules, papules, or nodules present. Ultrasound of the lower extremity is negative for deep vein thrombosis or skin abscess. The blood cultures are pending. Which of the following is the most likely diagnosis based on history and physical examination? | E15: Answer: B Reasoning: The patient presents with poorly demarcated erythema, edema, warmth, and tenderness on the right leg with a skin break, consistent with cellulitis. Erysipelas typically has well-demarcated, raised borders and involves more superficial layers. The absence of vesicles, pustules, or gas formation rules out folliculitis and gas gangrene. Contact dermatitis would be pruritic rather than tender and lacks the infectious features. Confidence: 95% | F15: Anterior horn cell degeneration | G15: Yes | H15: 1 | I15: 1 | J15: 1 | K15: 1 | L15: 0 | M15: 1 | N15: 1 | O15: 1 | P15: =1-((ABS(H15-I15))+(ABS(J15-K15))+(ABS(L15-M15))+(ABS(N15-O15)))/4 -> 0.75 | U15: =(H15+J15+L15+N15)/4 -> 0.75 | V15: =(I15+K15+M15+O15)/4 -> 1
... A101: CV_049 | B101: Claude Opus | C101: few-shot | D101: A 55-year-old man is brought to the physician because of inappropriate behavior for the past 6 months. He has been making inappropriate comments and jokes while talking to friends and family members. He was arrested 3 weeks ago while trying to kiss strangers on the street. He has no interest in talking to his daughter or playing with his grandchildren. During this period, he has developed a strong desire for chocolate pudding and potato chips and has gained 10 kg (22 lb). He appears unkempt. Vital signs are within normal limits. Physical examination is unremarkable. Mental status examination shows apathy and a blunt affect. He avoids answering questions and instead comments on the individuals he saw in the waiting room. Mini-Mental State Examination score is 28/30. A complete blood count and serum concentrations of glucose, creatine, and electrolytes are within the reference range. Which of the following is the most likely diagnosis? | E101: A 55-year-old man presents with a 6-month history of inappropriate social behavior, personality changes, apathy, and specific food cravings with weight gain. Let me analyze each option: **Key Clinical Features:** - Inappropriate social behavior (comments, jokes, kissing strangers) - Loss of social inhibition - Apathy and loss of interest in family - Blunt affect - Specific food cravings (chocolate pudding, potato chips) - hyperorality - Preserved cognition (MMSE 28/30) - Normal physical examination - Normal laboratory findings **Analysis of Options:** **A. Parkinson disease:** Primarily a movement disorder with tremor, rigidity, and bradykinesia. While dementia can occur late in the disease, the prominent early behavioral and personality changes without motor symptoms make this unlikely. **B. Amyotrophic lateral sclerosis (ALS):** Primarily affects motor neurons causing weakness and muscle wasting. While frontotemporal dementia can overlap with ALS, the absence of motor symptoms and pure behavioral presentation makes this less likely. **C. Normal pressure hydrocephalus:** Classic triad includes gait disturbance, urinary incontinence, and dementia. This patient has normal gait and no mention of incontinence. **D. Wilson disease:** Presents with liver disease, neurological symptoms (movement disorders), and Kayser-Fleischer rings. Typically presents in younger patients (teens-30s). Normal physical exam and labs make this unlikely. **E. Frontotemporal dementia (FTD):** This fits perfectly with: - Behavioral variant FTD characteristics - Early personality and behavioral changes - Loss of social awareness and disinhibition - Apathy - Hyperorality and dietary changes (specific food preferences) - Relatively preserved memory and cognition early on (high MMSE) - Typical age of onset (45-65 years) **Answer: E** **Reasoning:** The constellation of disinhibited behavior, loss of empathy, apathy, hyperorality with specific food cravings, and preserved cognition (MMSE 28/30) is classic for behavioral variant frontotemporal dementia. FTD characteristically presents with prominent personality and behavioral changes before significant memory impairment, distinguishing it from Alzheimer's disease. The frontal lobe dysfunction explains the social disinhibition and inappropriate behavior. **Confidence: 95%** | F101: Embryonal carcinoma | G101: Yes | H101: 1 | I101: 1 | J101: 1 | K101: 1 | L101: 0.5 | M101: 1 | N101: 1 | O101: 1 | P101: =1-((ABS(H101-I101))+(ABS(J101-K101))+(ABS(L101-M101))+(ABS(N101-O101)))/4 -> 0.875 | U101: =(H101+J101+L101+N101)/4 -> 0.875 | V101: =(I101+K101+M101+O101)/4 -> 1
A102: CV_050 | B102: Claude Opus | C102: few-shot | D102: A 32-year-old Caucasian man presents to the physician because of the swelling and discomfort of the right testis for 3 weeks. There is no history of trauma, fever, or night sweats. He had surgery for an undescended right testis when he was 6 months old. There is no history of liver disease or hypogonadism. He has fathered 2 children. He takes no medications and denies any illicit drug use. The vital signs are within normal limits. Palpation of the scrotum reveals a firm nontender mass that cannot be separated from the right testis. Examination of the left testis shows no abnormalities. There is no supraclavicular or inguinal lymphadenopathy. Gynecomastia is present. The rest of the physical examination is unremarkable. Ultrasound shows an enlarged right testicle with a hypoechoic mass replacing a large portion of the normal architecture. The left testis is normal. The laboratory test results are as follows: HCG Elevated AFP Elevated LDH Normal Which of the following is the most likely diagnosis? | E102: **Answer: A** **Reasoning:** This patient presents with several key features pointing toward a testicular germ cell tumor: 1. **Risk factor**: History of cryptorchidism (undescended testis), which increases testicular cancer risk 5-10 fold, even after orchiopexy 2. **Age**: 32 years old, typical age for germ cell tumors (peak incidence 20-40 years) 3. **Clinical presentation**: Firm, nontender testicular mass that cannot be separated from the testis 4. **Imaging**: Hypoechoic mass replacing testicular architecture (classic for malignancy) 5. **Gynecomastia**: Present, indicating hormone production by the tumor 6. **Laboratory findings**: - **Both HCG and AFP are elevated** - LDH is normal The elevation of **both HCG and AFP** is the critical distinguishing feature: - **Seminoma**: Produces elevated HCG in ~15% of cases, but **AFP is never elevated** in pure seminoma - **Embryonal carcinoma**: Can produce **both HCG and AFP**, and often presents as a mixed germ cell tumor - **Leydig cell tumor**: Would produce testosterone/estrogen (causing gynecomastia) but not typically HCG or AFP - **Lymphoma**: Would not produce these tumor markers - **Metastasis**: Less likely in a young patient without known primary; would not typically produce both markers The combination of elevated HCG AND AFP essentially rules out pure seminoma and points to a non-seminomatous germ cell tumor, most commonly embryonal carcinoma or mixed germ cell tumor containing embryonal elements. **Confidence: 94%** | G102: Yes | H102: 1 | I102: 1 | J102: 1 | K102: 1 | L102: 1 | M102: 1 | N102: 1 | O102: 1 | P102: =1-((ABS(H102-I102))+(ABS(J102-K102))+(ABS(L102-M102))+(ABS(N102-O102)))/4 -> 1 | U102: =(H102+J102+L102+N102)/4 -> 1 | V102: =(I102+K102+M102+O102)/4 -> 1
A103: CV_001 | B103: Claude Opus | C103: chain-of-thought | D103: A 9-year-old girl is brought to the pediatrician for a wellness checkup. The girl's past medical history is non-contributory, and she has met all her developmental milestones. Her parents were recently called into the office as the girl was found touching the genitals of one of her classmates. She was trying to insert a toy into her classmate's genitals. The girl is asked what has happened and what she thinks is going on but she is too shy to reply to the physician. The girl and her mother recently moved in with a family member. They live in low-income housing subsidized by the government and are currently on food stamps. The mother states that her daughter has been particularly argumentative lately and that they have gotten into arguments in which her daughter screamed at her and locked herself in the bathroom. Which of the following is the most likely diagnosis? | E103: Reasoning: This case presents several concerning findings that warrant careful analysis. The key clinical detail is the sexually inappropriate behavior of a 9-year-old girl attempting to insert a toy into another child's genitals. While some sexual curiosity is developmentally normal in young children, this behavior is advanced, coercive, and mimics adult sexual activity in a way that is highly unusual for this age group. Children who have been sexually abused often exhibit age-inappropriate sexual knowledge and behaviors, including attempting to engage peers in sexual acts that replicate what they have experienced. The recent move to live with a family member creates a new environmental risk factor. The child's reluctance to speak with the physician and recent behavioral changes (argumentativeness, isolating herself) are consistent with trauma response and emotional distress. While adjustment disorder could explain some behavioral changes after a move, it does not account for the specific sexual behaviors. ADHD and precocious puberty would not cause this type of sexually coercive behavior. This is not a normal developmental variant, as the behavior described is far beyond age-appropriate sexual exploration. The constellation of sexually inappropriate and aggressive behavior toward peers, recent change in living situation, behavioral changes, and reluctance to communicate strongly suggests sexual abuse. Answer: E Confidence: 92% | F103: Sexual abuse | G103: Yes | H103: 1 | I103: 1 | J103: 1 | K103: 1 | L103: 1 | M103: 1 | N103: 1 | O103: 1 | P103: =1-((ABS(H103-I103))+(ABS(J103-K103))+(ABS(L103-M103))+(ABS(N103-O103)))/4 -> 1 | U103: =(H103+J103+L103+N103)/4 -> 1 | V103: =(I103+K103+M103+O103)/4 -> 1
A104: CV_002 | B104: Claude Opus | C104: chain-of-thought | D104: An obese 50-year-old woman presents to the emergency department of a rural hospital due to chest pain for the last 12 hours. The pain is substernal, crushing in nature, radiating into her neck, and accompanied by profuse sweating. Her history is significant for hypertension, and she admits poor compliance with her medications. An ECG done at the clinic confirmed the presence of STEMI, and the patient was given aspirin. The ambulance was in an accident on the way to the hospital and by the time the patient reached the angiography suite, the cardiologist decided intervention should be delayed due to the late presentation. Also, the patient’s pain has improved. The patient is admitted and is stable for 3 nights with no dyspnea or edema. Her blood pressure is kept under control while in the hospital. On the fourth night, the patient becomes quite agitated and soon thereafter she is unresponsive. Her pulse cannot be palpated. She has an elevated JVP and upon auscultation, heart sounds are distant. What is the most likely diagnosis for this patient? | E104: Reasoning: This patient presented with STEMI but did not receive timely reperfusion therapy (angiography was delayed). She remained stable for 3 days, then suddenly became agitated and unresponsive with loss of pulse. The key clinical findings are: 1. **Elevated JVP** - indicates increased right atrial pressure 2. **Distant heart sounds** - suggests fluid in the pericardial space muffling heart sounds 3. **Loss of pulse with these findings** - classic Beck's triad (hypotension, elevated JVP, muffled heart sounds) indicating cardiac tamponade The timeline is critical: mechanical complications of MI typically occur at specific times post-infarction. Free wall rupture occurs 3-5 days post-MI when the infarcted myocardium is most vulnerable (maximal softening before scar formation). The sudden hemodynamic collapse with tamponade physiology (elevated JVP, distant heart sounds, pulselessness) is pathognomonic for left ventricular free wall rupture leading to hemopericardium and cardiac tamponade. VSR and papillary muscle rupture would present with new murmurs and pulmonary edema. Acute pericarditis would have preceded this event with chest pain and friction rub. Pulmonary embolism wouldn't explain the distant heart sounds. Answer: C Confidence: 95% | F104: Left ventricular free wall rupture | G104: Yes | H104: 1 | I104: 1 | J104: 1 | K104: 1 | L104: 1 | M104: 1 | N104: 1 | O104: 1 | P104: =1-((ABS(H104-I104))+(ABS(J104-K104))+(ABS(L104-M104))+(ABS(N104-O104)))/4 -> 1 | U104: =(H104+J104+L104+N104)/4 -> 1 | V104: =(I104+K104+M104+O104)/4 -> 1
A105: CV_003 | B105: Claude Opus | C105: chain-of-thought | D105: A 6-year-old boy is brought to the physician because of inability to concentrate and difficulties completing assignments at school. His mother says that he frequently interrupts others during conversations at home and that his teachers often reprimand him for talking excessively in school. He refuses to play with the other children and often has physical altercations with his classmates. He can jump up and down but he cannot hop on one foot. He eats without assistance but has difficulty using silverware. He cannot follow three-step directions. There is no family history of serious illness. Examination shows a small head, wide-spaced eyes, and short palpebral fissures. His upper lip is thin and flat. He has a sunken nasal bridge and a small jaw. There is a 3/6 pansystolic murmur heard along the left lower sternal border. Which of the following is the most likely cause of these findings? | E105: Reasoning: This 6-year-old boy presents with behavioral problems (poor concentration, impulsivity, excessive talking, aggression), developmental delays (cannot hop on one foot, difficulty with silverware, cannot follow three-step directions), and distinctive dysmorphic features. The key physical findings include microcephaly (small head), wide-spaced eyes (hypertelorism), short palpebral fissures, thin and flat upper lip, sunken nasal bridge, and small jaw (micrognathia). Additionally, he has a cardiac abnormality indicated by the pansystolic murmur, suggesting a ventricular septal defect. This constellation of findings—particularly the facial features (smooth philtrum/thin upper lip, short palpebral fissures, micrognathia), microcephaly, developmental delays, behavioral problems, and cardiac defect—is highly characteristic of fetal alcohol syndrome (FAS). The facial features described are classic for prenatal alcohol exposure. Down syndrome (trisomy 21) would present with different facial features including upslanting palpebral fissures and protruding tongue. Williams syndrome (deletion of chromosome 7) presents with elfin facies and is associated with hypercalcemia. Fragile X syndrome typically presents with large ears, long face, and macro-orchidism in males. Fetal hydantoin syndrome (phenytoin exposure) can have some overlapping features but the classic triad of FAS features makes prenatal alcohol exposure most likely. Answer: C Confidence: 95% | F105: Prenatal alcohol exposure | G105: Yes | H105: 1 | I105: 1 | J105: 1 | K105: 1 | L105: 1 | M105: 1 | N105: 1 | O105: 1 | P105: =1-((ABS(H105-I105))+(ABS(J105-K105))+(ABS(L105-M105))+(ABS(N105-O105)))/4 -> 1 | U105: =(H105+J105+L105+N105)/4 -> 1 | V105: =(I105+K105+M105+O105)/4 -> 1
A106: CV_004 | B106: Claude Opus | C106: chain-of-thought | D106: A 57-year-old man presents with 2 days of severe, generalized, abdominal pain that is worse after meals. He is also nauseated and reports occasional diarrhea mixed with blood. Apart from essential hypertension, his medical history is unremarkable. His vital signs include a temperature of 36.9°C (98.4°F), blood pressure of 145/92 mm Hg, and an irregularly irregular pulse of 105/min. Physical examination is only notable for mild periumbilical tenderness. Which of the following is the most likely diagnosis? | E106: Reasoning: This 57-year-old man presents with severe, generalized abdominal pain that worsens after meals (postprandial pain), along with nausea and bloody diarrhea. The key finding is an "irregularly irregular pulse of 105/min," which is pathognomonic for atrial fibrillation. The classic triad of acute mesenteric ischemia includes: (1) severe abdominal pain out of proportion to physical examination findings (he has only mild periumbilical tenderness despite severe pain), (2) postprandial pain (intestinal angina), and (3) a cardiac source of emboli. Atrial fibrillation is the most common source of emboli to the superior mesenteric artery, causing acute mesenteric ischemia. The bloody diarrhea represents mucosal sloughing from ischemic bowel. Acute pancreatitis typically presents with epigastric pain radiating to the back and elevated lipase. Crohn's disease has a more chronic presentation. Diverticular disease usually presents with left lower quadrant pain. Gastroenteritis would not explain the severe pain out of proportion to exam or the atrial fibrillation context. Answer: C Confidence: 95% | F106: Acute mesenteric ischemia | G106: Yes | H106: 1 | I106: 1 | J106: 1 | K106: 1 | L106: 1 | M106: 1 | N106: 1 | O106: 1 | P106: =1-((ABS(H106-I106))+(ABS(J106-K106))+(ABS(L106-M106))+(ABS(N106-O106)))/4 -> 1 | U106: =(H106+J106+L106+N106)/4 -> 1 | V106: =(I106+K106+M106+O106)/4 -> 1
A107: CV_005 | B107: Claude Opus | C107: chain-of-thought | D107: A 5-year-old male is brought to the pediatrician by his mother, who relates a primary complaint of a recent history of five independent episodes of vomiting over the last 10 months, most recently 3 weeks ago. Each time, he has awoken early in the morning appearing pale, feverish, lethargic, and complaining of severe nausea. This is followed by 8-12 episodes of non-bilious vomiting over the next 24 hours. Between these episodes he returns to normal activity. He has no significant past medical history and takes no other medications. Review of systems is negative for changes in vision, gait disturbance, or blood in his stool. His family history is significant only for migraine headaches. Vital signs and physical examination are within normal limits. Initial complete blood count, comprehensive metabolic panel, and abdominal radiograph were unremarkable. What is the most likely diagnosis? | E107: Reasoning: This 5-year-old boy presents with a classic pattern of episodic, stereotypical vomiting attacks occurring over 10 months. Key features include: (1) discrete episodes separated by symptom-free intervals where he returns to normal activity, (2) each episode begins early in the morning with prodromal symptoms (pallor, fever, lethargy, nausea), (3) followed by intense, non-bilious vomiting lasting approximately 24 hours, and (4) complete resolution between episodes. The family history of migraine headaches is particularly significant, as cyclic vomiting syndrome (CVS) is strongly associated with personal or family history of migraines and is considered part of the migraine spectrum disorders in children. The normal physical examination, vital signs, and unremarkable laboratory/imaging studies rule out structural or acute pathological causes. Reye's syndrome presents with acute encephalopathy and is not episodic. An intracranial mass would typically show progressive symptoms or neurological findings. GERD doesn't present with such discrete, severe episodic patterns. Intussusception is an acute surgical emergency with bloody stools and would not have a 10-month recurring course. Answer: C Confidence: 95% | F107: Cyclic vomiting syndrome | G107: Yes | H107: 1 | I107: 1 | J107: 1 | K107: 1 | L107: 1 | M107: 1 | N107: 1 | O107: 1 | P107: =1-((ABS(H107-I107))+(ABS(J107-K107))+(ABS(L107-M107))+(ABS(N107-O107)))/4 -> 1 | U107: =(H107+J107+L107+N107)/4 -> 1 | V107: =(I107+K107+M107+O107)/4 -> 1
A108: CV_006 | B108: Claude Opus | C108: chain-of-thought | D108: A 45-year-old man comes to the emergency department with the complaint of pain and swelling of the proximal joint in the third finger of his right hand. The pain is so severe that it woke him up from sleep this morning. He has never had an episode like this before. The patient has smoked a pack of cigarettes daily for the last 25 years and drinks alcohol heavily each weekend. His friend threw a party last night where he drank 3–4 beers and was unable to drive back home. He has no past medical illness. His mother died of pancreatic cancer at age 55, and his father died of a stroke 2 years ago. His temperature is 37.7°C (100°F), blood pressure is 130/70 mm Hg, pulse is 104/min, respiratory rate is 20/min, and BMI is 25 kg/m2. The patient is in moderate distress due to the pain. On examination, the proximal interphalangeal joint of the third finger of his right hand is very tender to touch, swollen, warm, and slightly red in color. Range of motion cannot be assessed due to extreme tenderness. The patient’s right hand is shown in the image. Laboratory investigation Complete blood count: Hemoglobin 14.5 g/dL Leukocytes 16,000/mm3 Platelets 150,000/mm3 ESR 55mm/hr Synovial fluid is aspirated from the joint. The findings are: Appearance Cloudy, dense yellow WBC 30,000 cells/µL Culture Negative Negatively birefringent needle-shaped crystals are seen. Which of the following is the most likely diagnosis? | E108: Reasoning: This patient presents with acute onset of severe joint pain in the proximal interphalangeal (PIP) joint that woke him from sleep, which is characteristic of an acute inflammatory arthritis. Key diagnostic features include: 1. **Synovial fluid analysis**: The presence of negatively birefringent needle-shaped crystals is pathognomonic for monosodium urate crystals, which confirm gout. In contrast, pseudogout shows positively birefringent rhomboid crystals (calcium pyrophosphate). 2. **Clinical presentation**: Acute onset of severe monoarticular arthritis with warmth, erythema, and swelling is classic for acute gout. The severity that awakens the patient from sleep is typical of gout attacks. 3. **Risk factors**: Alcohol consumption (especially beer, which is high in purines) is a well-known precipitant of gout attacks, and the patient consumed 3-4 beers the night before symptom onset. 4. **Laboratory findings**: Elevated WBC (16,000), ESR (55), and synovial fluid WBC (30,000) all support acute inflammatory arthritis. The negative culture rules out septic arthritis. 5. **First episode**: The patient states he has never had an episode like this before, making this an acute (first) presentation rather than chronic gout. Answer: D Confidence: 99% | F108: Acute gout | G108: Yes | H108: 1 | I108: 1 | J108: 1 | K108: 1 | L108: 1 | M108: 1 | N108: 1 | O108: 1 | P108: =1-((ABS(H108-I108))+(ABS(J108-K108))+(ABS(L108-M108))+(ABS(N108-O108)))/4 -> 1 | U108: =(H108+J108+L108+N108)/4 -> 1 | V108: =(I108+K108+M108+O108)/4 -> 1
A109: CV_007 | B109: Claude Opus | C109: chain-of-thought | D109: A 61-year-old man comes to the physician because of fatigue, diarrhea, and crampy abdominal pain for 3 weeks. The abdominal pain is worse after eating. During the past week, he has had up to 4 watery stools daily. He has also had pain in his mouth and gums for 6 days. He has not had nausea, vomiting, or fever. Four months ago, he went on a 1-week trip to the Dominican Republic. He has atrial fibrillation, hypertension, and hypothyroidism. Current medications include levothyroxine, metoprolol, and warfarin. He has smoked one pack of cigarettes daily for 40 years. His temperature is 37.9°C (100.2°F), pulse is 81/min, and blood pressure is 120/75 mm Hg. Examination shows two 1-cm, tender ulcerative lesions in the mouth. Abdominal examination shows mild tenderness to palpation in the right lower quadrant without guarding or rebound. Bowel sounds are normal. His hemoglobin concentration is 11.5 g/dL, mean corpuscular volume is 77 fL, leukocyte count is 11,800 mm3, and platelet count is 360,000 mm3. Colonoscopy with biopsy of the colonic mucosa is performed. Analysis of the specimen shows non-caseating granulomas and neutrophilic inflammation of the crypts. Which of the following is the most likely diagnosis? | E109: Reasoning: This 61-year-old man presents with chronic diarrhea, crampy abdominal pain (worse after eating), fatigue, and oral ulcers. Key laboratory findings include microcytic anemia (MCV 77 fL, Hgb 11.5 g/dL) and leukocytosis. The colonoscopy biopsy shows non-caseating granulomas and neutrophilic crypt inflammation (crypt abscesses), which are hallmark pathologic features of Crohn disease. The oral ulcers (aphthous ulcers) are a common extraintestinal manifestation of inflammatory bowel disease. The right lower quadrant tenderness corresponds to typical ileocecal involvement in Crohn disease. The microcytic anemia likely reflects chronic inflammation and iron deficiency from intestinal blood loss. While the Dominican Republic trip raises consideration of tropical infections, the biopsy findings are not consistent with tropical sprue (which shows villous atrophy without granulomas) or infectious causes. Diverticulitis typically presents acutely with left lower quadrant pain, not chronic symptoms with granulomas. Celiac disease shows villous atrophy without granulomas. Whipple disease shows PAS-positive macrophages, not granulomas. Answer: C Confidence: 95% | F109: Crohn disease | G109: Yes | H109: 1 | I109: 1 | J109: 1 | K109: 1 | L109: 1 | M109: 1 | N109: 1 | O109: 1 | P109: =1-((ABS(H109-I109))+(ABS(J109-K109))+(ABS(L109-M109))+(ABS(N109-O109)))/4 -> 1 | U109: =(H109+J109+L109+N109)/4 -> 1 | V109: =(I109+K109+M109+O109)/4 -> 1
A110: CV_008 | B110: Claude Opus | C110: chain-of-thought | D110: A 6-year-old boy is brought to the physician because he has a limp for 3 weeks. He was born at term and has been healthy since. His immunization are up-to-date; he received his 5th DTaP vaccine one month ago. He is at 50th percentile for height and weight. His temperature is 37°C (98.6°F), pulse is 80/min and respirations are 28/min. When asked to stand only on his right leg, the left pelvis sags. The remainder of the examination shows no abnormalities. Which of the following is the most likely cause of these findings? | E110: Reasoning: The key finding here is a positive Trendelenburg sign - when the patient stands on his right leg, the left pelvis sags. This indicates weakness of the hip abductors on the stance side (right side). The hip abductors (primarily gluteus medius and minimus) are responsible for stabilizing the pelvis during single-leg stance and are innervated by the superior gluteal nerve. When these muscles are weak or their nerve supply is damaged, the contralateral pelvis drops when standing on the affected side. The patient stands on the RIGHT leg and the LEFT pelvis sags, indicating weakness of the RIGHT hip abductors, which would be caused by damage to the RIGHT superior gluteal nerve. The inferior gluteal nerve innervates the gluteus maximus (hip extension), not the hip abductors. L5 radiculopathy could cause some hip abductor weakness but would typically present with additional findings. The common peroneal nerve affects foot dorsiflexion/eversion, not hip abduction. A spinal abscess would likely present with fever, back pain, and more systemic symptoms. The recent DTaP vaccine and 3-week duration with otherwise healthy child suggests this could be related to an injection injury to the superior gluteal nerve in the right buttock. Answer: E Confidence: 95% | F110: Damage to the right superior gluteal nerve | G110: Yes | H110: 1 | I110: 1 | J110: 1 | K110: 1 | L110: 1 | M110: 1 | N110: 1 | O110: 1 | P110: =1-((ABS(H110-I110))+(ABS(J110-K110))+(ABS(L110-M110))+(ABS(N110-O110)))/4 -> 1 | U110: =(H110+J110+L110+N110)/4 -> 1 | V110: =(I110+K110+M110+O110)/4 -> 1
A111: CV_009 | B111: Claude Opus | C111: chain-of-thought | D111: A 3-year-old boy presents with fever, generalized fatigue, nausea, and progressive anemia. The patient’s mother says his condition was normal until one week ago when he started having flu-like symptoms such as fever, general fatigue, and abdominal discomfort. Past medical experience is significant for sickle cell disease, diagnosed 2 years ago. His vital signs include: blood pressure 98/50 mm Hg, pulse 120/min, temperature 39.0℃ (102.0℉). On physical examination, the patient is crying excessively and his skin and the conjunctivae look pale. Splenomegaly is noted. There is no skin rash nor lymphadenopathy. Laboratory findings are significant for the following: Total WBC count 22,000/mm3 Neutrophils 35% Lymphocytes 44% Atypical lymphocytes 9% Monocytes 12% RBC 1. 6 million/mm3 Hb 5.4 g/dL Hct 14.4% MCV 86 fL MCHC 37.5% Reticulocytes 0.1% A peripheral blood smear shows sickle cells. A direct and indirect Coombs test is negative. Which of the following is the most likely cause of this patient’s most recent symptoms? | E111: Reasoning: This 3-year-old boy with known sickle cell disease presents with acute worsening anemia and fever. The key laboratory findings are: - Severely low hemoglobin (5.4 g/dL) and hematocrit (14.4%) - Critically low reticulocyte count (0.1%) - this indicates absent bone marrow compensation - Normal MCV (86 fL) and MCHC (37.5%) - Negative Coombs tests ruling out immune-mediated hemolysis In sickle cell disease patients, the baseline hemolysis typically triggers a compensatory reticulocytosis. The sudden development of severe anemia WITH reticulocytopenia (aplastic crisis) is pathognomonic for parvovirus B19 infection. Parvovirus B19 specifically targets erythroid progenitor cells in the bone marrow, causing temporary arrest of red blood cell production. The flu-like prodrome (fever, fatigue) followed by progressive anemia fits this diagnosis perfectly. The splenomegaly can be seen in sickle cell disease patients who still have functional splenic tissue at age 3. IgG-mediated hemolytic anemia is ruled out by negative Coombs tests. Sickle cell disease itself doesn't explain the acute change with reticulocytopenia. Myelofibrosis and Fanconi's anemia don't present this way acutely with preceding viral symptoms. Answer: A Confidence: 98% | F111: Parvovirus infection | G111: Yes | H111: 1 | I111: 1 | J111: 1 | K111: 1 | L111: 1 | M111: 1 | N111: 1 | O111: 1 | P111: =1-((ABS(H111-I111))+(ABS(J111-K111))+(ABS(L111-M111))+(ABS(N111-O111)))/4 -> 1 | U111: =(H111+J111+L111+N111)/4 -> 1 | V111: =(I111+K111+M111+O111)/4 -> 1
A112: CV_010 | B112: Claude Opus | C112: chain-of-thought | D112: A 40-year-old woman comes to the emergency department because of difficulty walking for the past 4 hours. She first noticed her symptoms after getting up this morning and her foot dragging while walking. She feels tired. She has a history of chronic sinusitis. Six months ago, she was diagnosed with asthma. Current medications include an albuterol inhaler and inhaled corticosteroids. Her temperature is 38.9°C (102°F), pulse is 80/min, and her blood pressure is 140/90 mm Hg. Auscultation of her lungs shows diffuse wheezing over bilateral lung fields. Physical examination shows tender subcutaneous nodules on the extensor surfaces of the elbows. There are palpable, non-blanching erythematous lesions on both shins. Dorsiflexion of the right foot is impaired. Sensation to pinprick, light touch, and vibration is decreased over the ulnar aspect of the left forearm. Laboratory studies show: Hemoglobin 11.3 g/dL Leukocyte count 24,500 Segmented neutrophils 48% Eosinophils 29% Lymphocytes 19% Monocytes 4% Platelet count 290,000/mm3 Serum Urea nitrogen 32 mg/dL Creatinine 1.85 mg/dL Urine Blood 2+ Protein 3+ Which of the following is the most likely diagnosis in this patient?" | E112: Reasoning: This patient presents with a constellation of findings highly suggestive of a systemic vasculitis. Key features include: (1) history of asthma and chronic sinusitis, (2) marked eosinophilia (29%, which is significantly elevated), (3) mononeuritis multiplex (foot drop from right peroneal nerve involvement and ulnar nerve sensory deficit), (4) pulmonary involvement with wheezing, (5) renal involvement (elevated creatinine, hematuria, proteinuria), (6) subcutaneous nodules and palpable purpura, and (7) fever and leukocytosis. The combination of asthma, chronic sinusitis, marked eosinophilia, and systemic vasculitis affecting multiple organs (lungs, kidneys, peripheral nerves) is classic for eosinophilic granulomatosis with polyangiitis (EGPA, formerly Churg-Strauss syndrome). Granulomatosis with polyangiitis would typically present with upper respiratory tract involvement but without prominent eosinophilia or asthma history. Goodpasture syndrome primarily affects lungs and kidneys but lacks peripheral nerve involvement, eosinophilia, and skin findings. Henoch-Schönlein purpura typically occurs in children and lacks prominent pulmonary and neurologic features. Excessive glucocorticoid use would not explain the vasculitis picture. Answer: E Confidence: 95% | F112: Eosinophilic granulomatosis with polyangiitis " | G112: Yes | H112: 1 | I112: 1 | J112: 1 | K112: 1 | L112: 1 | M112: 1 | N112: 1 | O112: 1 | P112: =1-((ABS(H112-I112))+(ABS(J112-K112))+(ABS(L112-M112))+(ABS(N112-O112)))/4 -> 1 | U112: =(H112+J112+L112+N112)/4 -> 1 | V112: =(I112+K112+M112+O112)/4 -> 1
A113: CV_011 | B113: Claude Opus | C113: chain-of-thought | D113: A 64-year-old woman comes to the physician for a follow-up examination. She has had difficulty reading for the past 6 months. She tried using multiple over-the-counter glasses with different strengths, but they have not helped. She has hypertension and type 2 diabetes mellitus. Current medications include insulin and enalapril. Her temperature is 37.1°C (98.8°F), pulse is 80/min, and blood pressure is 126/84 mm Hg. The pupils are round and react sluggishly to light. Visual acuity in the left eye is 6/60 and in the right eye counting fingers at 6 feet. Fundoscopy shows pallor of the optic disc bilaterally. The cup-to-disk ratio is 0.7 in the left eye and 0.9 in the right eye (N = 0.3). Which of the following is the most likely diagnosis? | E113: Reasoning: This 64-year-old woman with hypertension and type 2 diabetes presents with progressive vision loss over 6 months that is not corrected by glasses. Key clinical findings include: 1. Sluggish pupillary light reflexes bilaterally 2. Significantly reduced visual acuity (worse in right eye - counting fingers at 6 feet) 3. Bilateral optic disc pallor on fundoscopy 4. Markedly increased cup-to-disc ratios (0.7 left, 0.9 right; normal ~0.3) The increased cup-to-disc ratio indicates optic nerve cupping, which is characteristic of glaucomatous optic neuropathy. The bilateral presentation, gradual progressive vision loss, and optic disc pallor with pathologic cupping strongly suggest open-angle glaucoma. This chronic condition causes painless, gradual peripheral-to-central vision loss due to increased intraocular pressure damaging the optic nerve. Hypertensive retinopathy would show arteriovenous nicking, flame hemorrhages, and cotton-wool spots. Age-related macular degeneration affects central vision primarily with drusen or neovascularization. Diabetic retinopathy would show microaneurysms, hemorrhages, and exudates. Optic neuritis typically presents acutely with pain on eye movement and doesn't cause this degree of optic cupping. Answer: D Confidence: 95% | F113: Open-angle glaucoma | G113: Yes | H113: 1 | I113: 1 | J113: 1 | K113: 1 | L113: 1 | M113: 1 | N113: 1 | O113: 1 | P113: =1-((ABS(H113-I113))+(ABS(J113-K113))+(ABS(L113-M113))+(ABS(N113-O113)))/4 -> 1 | U113: =(H113+J113+L113+N113)/4 -> 1 | V113: =(I113+K113+M113+O113)/4 -> 1
A114: CV_012 | B114: Claude Opus | C114: chain-of-thought | D114: A 53-year-old male presents to your office for abdominal discomfort. The patient states he first noticed pain on his right flank several months ago, and it has been gradually getting worse. For the past week, he has also noticed blood in his urine. Prior to this episode, he has been healthy and does not take any medications. The patient denies fever, chills, and dysuria. He has a 40 pack-year smoking history. Vital signs are T 37 C, HR 140/90 mmHg, HR 84/min, RR 14/min, O2 98%. Physical exam is unremarkable. CBC reveals a hemoglobin of 17 and hematocrit of 51%, and urinalysis is positive for red blood cells, negative for leukocytes. Which of the following is the most likely diagnosis? | E114: Reasoning: This patient presents with a classic triad suggestive of renal pathology: flank pain, hematuria, and a palpable mass (though not explicitly mentioned here). Key findings include: 1. **Hematuria with flank pain** in a middle-aged male with significant smoking history (40 pack-years) - smoking is a major risk factor for renal cell carcinoma (RCC) 2. **Polycythemia** - elevated hemoglobin (17) and hematocrit (51%) suggest erythrocytosis. RCC is a well-known cause of paraneoplastic erythrocytosis due to ectopic erythropoietin production 3. **Age and demographics** - RCC typically presents in the 50s-70s, more common in males 4. **Absence of infectious symptoms** - no fever, chills, or dysuria, and urinalysis is negative for leukocytes, making pyelonephritis unlikely 5. **Gradual progression** over months is consistent with malignancy Polycystic kidney disease would typically present bilaterally with positive family history. AAA wouldn't cause hematuria. Pyelonephritis is ruled out by lack of infection signs. Renal oncocytoma is benign and rarely causes paraneoplastic syndromes like erythrocytosis. The combination of hematuria, flank pain, smoking history, and paraneoplastic erythrocytosis strongly points to RCC. Answer: A Confidence: 95% | F114: Renal cell carcinoma | G114: Yes | H114: 1 | I114: 1 | J114: 0.5 | K114: 1 | L114: 1 | M114: 1 | N114: 1 | O114: 1 | P114: =1-((ABS(H114-I114))+(ABS(J114-K114))+(ABS(L114-M114))+(ABS(N114-O114)))/4 -> 0.875 | U114: =(H114+J114+L114+N114)/4 -> 0.875 | V114: =(I114+K114+M114+O114)/4 -> 1
... A152: CV_050 | B152: Claude Opus | C152: chain-of-thought | D152: A 32-year-old Caucasian man presents to the physician because of the swelling and discomfort of the right testis for 3 weeks. There is no history of trauma, fever, or night sweats. He had surgery for an undescended right testis when he was 6 months old. There is no history of liver disease or hypogonadism. He has fathered 2 children. He takes no medications and denies any illicit drug use. The vital signs are within normal limits. Palpation of the scrotum reveals a firm nontender mass that cannot be separated from the right testis. Examination of the left testis shows no abnormalities. There is no supraclavicular or inguinal lymphadenopathy. Gynecomastia is present. The rest of the physical examination is unremarkable. Ultrasound shows an enlarged right testicle with a hypoechoic mass replacing a large portion of the normal architecture. The left testis is normal. The laboratory test results are as follows: HCG Elevated AFP Elevated LDH Normal Which of the following is the most likely diagnosis? | E152: Reasoning: This 32-year-old man presents with a firm testicular mass and has key risk factors and findings pointing toward a specific testicular tumor: 1. **Risk factors**: History of cryptorchidism (undescended testis) significantly increases risk for testicular germ cell tumors, even after orchiopexy. 2. **Clinical presentation**: Firm, nontender testicular mass with gynecomastia suggests hormone-producing tumor (HCG can cause gynecomastia through aromatization to estrogen). 3. **Tumor markers**: - Both HCG and AFP are elevated - LDH is normal 4. **Key marker analysis**: - Seminoma: Typically HCG may be mildly elevated in 10-20% of cases, but AFP is NEVER elevated in pure seminoma - Embryonal carcinoma: Can elevate both HCG and AFP - Leydig cell tumor: Sex cord-stromal tumor, would not typically elevate HCG or AFP significantly - Lymphoma: Would not elevate these germ cell markers - Metastasis: Less likely in young patient without primary cancer history 5. **Conclusion**: The elevation of BOTH HCG and AFP excludes pure seminoma and points toward a non-seminomatous germ cell tumor (NSGCT). Embryonal carcinoma is a common NSGCT that can produce both markers and frequently occurs in young men with cryptorchidism history. Answer: A Confidence: 90% | F152: Embryonal carcinoma | G152: Yes | H152: 1 | I152: 1 | J152: 1 | K152: 1 | L152: 1 | M152: 1 | N152: 1 | O152: 1 | P152: =1-((ABS(H152-I152))+(ABS(J152-K152))+(ABS(L152-M152))+(ABS(N152-O152)))/4 -> 1 | U152: =(H152+J152+L152+N152)/4 -> 1 | V152: =(I152+K152+M152+O152)/4 -> 1

Sheet Gemini
A1: LLM Clinical Vignette Evaluations | H1: Plausibility (0/0.5/1) | J1: Faithfulness (0/0.5/1) | L1: Calibration (0/0.5/1) | N1: Harmfulness (0/0.5/1) | Q1: Average Accuracy
A2: Case ID (This matches to the IDs in .json dataset) | B2: Model | C2: Prompt Type | D2: Vignette | E2: Text Output (Model Response) | F2: Correct Diagnosis | G2: Correct Diagnosis? (Y/N) | H2: Human Evaluation | I2: Model Self-Score | J2: Human Evaluation | K2: Model Self-Score | L2: Human Evaluation | M2: Model Self-Score | N2: Human Evaluation | O2: Model Self-Score | P2: Accuracy Score | Q2: Zero-shot | R2: Few-shot | S2: Chain-of-Thought | U2: Average Human Score | V2: Average Self Score | X2: Average Human Score (0) | Y2: Average Self Score (0) | Z2: Average Human Score (F) | AA2: Average Self Score (F) | AB2: Average Human Score (C) | AC2: Average Self Score (C)
A3: CV_001 | B3: Gemini | C3: zero-shot | D3: An 11-year-old girl is brought to her primary care physician by her mother with complaints of constant lower abdominal pain and foul-smelling urine for the past 2 days. The patient has had several previous episodes of simple urinary tract infections in the past. Her vitals signs show mild tachycardia without fever. Physical examination reveals suprapubic tenderness without costovertebral angle tenderness on percussion. Urinalysis reveals positive leukocyte esterase and nitrite. Further questioning reveals that the patient does not use the school toilets and holds her urine all day until she gets home. When pressed further, she gets teary-eyed and starts to cry and complains that other girls will make fun of her if she uses the bathroom and will spread rumors to the teachers and her friends. She reports that though this has never happened in the past it concerns her a great deal. Which of the following is the most likely diagnosis for this patient? Options: A. Social anxiety disorder B. Social phobia performance only C. Panic disorder D. Specific phobia E. Agoraphobia | E3: Answer: A Reasoning: The patient exhibits marked fear and anxiety about a specific social situation (using the school bathroom) due to a fear of negative evaluation and scrutiny by peers ("other girls will make fun of her," "spread rumors"). This fear is persistent, out of proportion to the actual threat, and significantly impacts her daily life, leading to recurrent urinary tract infections. These are the core diagnostic criteria for Social Anxiety Disorder. Confidence: 100% | F3: Social anxiety disorder | G3: Yes | H3: 1 | I3: 1 | J3: 1 | K3: 1 | L3: 0.5 | M3: 1 | N3: 1 | O3: 1 | P3: =1-((ABS(H3-I3))+(ABS(J3-K3))+(ABS(L3-M3))+(ABS(N3-O3)))/4 -> 0.875 | Q3: =AVERAGE(P3:P52) -> 0.9 | R3: =AVERAGE(P53:P102) -> 0.9875 | S3: =AVERAGE(P103:P152) -> 0.965 | U3: =(H3+J3+L3+N3)/4 -> 0.875 | V3: =(I3+K3+M3+O3)/4 -> 1 | X3: =AVERAGE(U3:U52) -> 0.9375 | Y3: =AVERAGE(V3:V52) -> 0.9375 | Z3: =AVERAGE(U53:U102) -> 0.97 | AA3: =AVERAGE(V53:V102) -> 0.9575 | AB3: =AVERAGE(U103:U152) -> 0.9375 | AC3: =AVERAGE(V103:V152) -> 0.9475
A4: CV_002 | B4: Gemini | C4: zero-shot | D4: A 4-year-old boy is brought to the physician for a well-child examination. He started walking at 20 months of age. He can use a cup to drink but cannot use silverware. He speaks in 2-word sentences and can build a tower of 4 blocks. He can scribble but cannot draw a circle. He is above the 99th percentile for height and at the 15th percentile for weight. Vital signs are within normal limits. Examination shows bilateral inferior lens dislocation. His fingers are long and slender. He has a high-arched palate. The thumb and 5th finger overlap when he grips a wrist with the opposite hand. The skin over the neck can be extended and stretched easily. Which of the following is the most likely cause of these findings? Options: A. Hypoxanthine-guanine-phosphoribosyl transferase deficiency B. Fibrillin 1 deficiency C. Type V collagen deficiency D. Cystathionine synthase deficiency E. Galactokinase deficiency | E4: Answer: D Reasoning: The patient presents with tall stature, arachnodactyly (long slender fingers, positive wrist sign), high-arched palate, bilateral inferior lens dislocation, and global developmental delay. This constellation of findings, particularly the inferior lens dislocation and intellectual disability, is highly characteristic of Homocystinuria, which is caused by cystathionine synthase deficiency. | F4: Cystathionine synthase deficiency | G4: Yes | H4: 1 | I4: 1 | J4: 1 | K4: 1 | L4: 1 | M4: 0 | N4: 1 | O4: 0 | P4: =1-((ABS(H4-I4))+(ABS(J4-K4))+(ABS(L4-M4))+(ABS(N4-O4)))/4 -> 0.5 | U4: =(H4+J4+L4+N4)/4 -> 1 | V4: =(I4+K4+M4+O4)/4 -> 0.5
A5: CV_003 | B5: Gemini | C5: zero-shot | D5: A 68-year-old male presents to your office for his annual physical exam. He has no complaints at this time and his chronic hypertension is well controlled. You notice a .5cm papule on the patient's eyelid that has a pink pearly appearance, rolled borders, and overlying telangiectasias. On further questioning, you find out the patient was a door-to-door salesman and spent a lot of time outdoors, and he did not wear sunscreen. He has fair skin and blonde hair. The patient states that he first noticed the lesion about 6 months prior, and it has grown slightly since then. What is the most likely diagnosis? Options: A. Squamous cell carcinoma B. Keratoacanthoma C. Verrucous carcinoma D. Basal cell carcinoma E. Actinic keratosis | E5: Answer: D Reasoning: The lesion's description as a "pink pearly papule" with "rolled borders" and "overlying telangiectasias" on the eyelid of an elderly patient with significant sun exposure and fair skin is the classic presentation of basal cell carcinoma. These features are highly specific for BCC compared to the other options. Confidence: 100% | F5: Basal cell carcinoma | G5: Yes | H5: 1 | I5: 1 | J5: 1 | K5: 1 | L5: 0.5 | M5: 1 | N5: 1 | O5: 1 | P5: =1-((ABS(H5-I5))+(ABS(J5-K5))+(ABS(L5-M5))+(ABS(N5-O5)))/4 -> 0.875 | U5: =(H5+J5+L5+N5)/4 -> 0.875 | V5: =(I5+K5+M5+O5)/4 -> 1
A6: CV_004 | B6: Gemini | C6: zero-shot | D6: A 78-year-old man is brought to the emergency department because of difficulty speaking. The symptoms began abruptly one hour ago while he was having breakfast with his wife. He has hypertension, type 2 diabetes mellitus, and coronary artery disease. Current medications include pravastatin, lisinopril, metformin, and aspirin. His temperature is 37°C (98.6°F), pulse is 76/min, and blood pressure is 165/90 mm Hg. He is right-handed. The patient speaks in short, simple sentences, and has difficulty repeating sequences of words. He can follow simple instructions. Right facial droop is present. Muscle strength is 4/5 on the right side and 5/5 on the left, and there is a mild right-sided pronator drift. Which of the following is the most likely cause of the patient's symptoms? Options: A. Occlusion of the right penetrating arteries B. Occlusion of the right middle cerebral artery C. Occlusion of the left middle cerebral artery D. Occlusion of the right posterior inferior cerebellar artery E. Rupture of left posterior cerebral artery malformation | E6: Answer: C Reasoning: The patient presents with abrupt onset of expressive aphasia (difficulty speaking, repeating words, but can follow simple instructions) and right-sided weakness (facial droop, hemiparesis, pronator drift). In a right-handed individual, expressive aphasia localizes to the dominant (left) cerebral hemisphere, specifically Broca's area. Right-sided motor deficits also localize to the contralateral (left) cerebral hemisphere. Both Broca's area and the motor cortex for the face and upper limb are supplied by the left middle cerebral artery. Confidence: 100% | F6: Occlusion of the left middle cerebral artery | G6: Yes | H6: 1 | I6: 1 | J6: 1 | K6: 1 | L6: 1 | M6: 1 | N6: 1 | O6: 1 | P6: =1-((ABS(H6-I6))+(ABS(J6-K6))+(ABS(L6-M6))+(ABS(N6-O6)))/4 -> 1 | U6: =(H6+J6+L6+N6)/4 -> 1 | V6: =(I6+K6+M6+O6)/4 -> 1
A7: CV_005 | B7: Gemini | C7: zero-shot | D7: A 48-year-old man comes to the physician because of worsening shortness of breath and nocturnal cough for the past 2 weeks. On two occasions, his cough was bloody. He had a heart condition as a child that was treated with antibiotics. He emigrated to the US from Kazakhstan 15 years ago. Pulmonary examination shows crackles at both lung bases. Cardiac examination is shown. Which of the following is the most likely diagnosis? Options: A. Aortic valve regurgitation B. Mitral valve prolapse C. Mitral valve stenosis D. Mitral valve regurgitation E. Tricuspid valve stenosis " | E7: Answer: C Reasoning: The patient's history of a childhood heart condition treated with antibiotics strongly suggests rheumatic fever, which commonly leads to mitral valve disease. The symptoms of worsening shortness of breath, nocturnal cough, hemoptysis (bloody cough), and pulmonary crackles are classic manifestations of pulmonary venous hypertension and edema, which are highly characteristic of mitral valve stenosis. Hemoptysis, in particular, is a strong indicator of severe mitral stenosis due due to rupture of congested pulmonary capillaries. Confidence: 95% | F7: Mitral valve stenosis | G7: Yes | H7: 1 | I7: 1 | J7: 1 | K7: 1 | L7: 1 | M7: 1 | N7: 1 | O7: 1 | P7: =1-((ABS(H7-I7))+(ABS(J7-K7))+(ABS(L7-M7))+(ABS(N7-O7)))/4 -> 1 | U7: =(H7+J7+L7+N7)/4 -> 1 | V7: =(I7+K7+M7+O7)/4 -> 1
A8: CV_006 | B8: Gemini | C8: zero-shot | D8: A 55-year-old man comes to the emergency department because of a dry cough and severe chest pain beginning that morning. Two months ago, he was diagnosed with inferior wall myocardial infarction and was treated with stent implantation of the right coronary artery. He has a history of hypertension and hypercholesterolemia. His medications include aspirin, clopidogrel, atorvastatin, and enalapril. His temperature is 38.5°C (101.3°F), pulse is 92/min, respirations are 22/min, and blood pressure is 130/80 mm Hg. Cardiac examination shows a high-pitched scratching sound best heard while sitting upright and during expiration. The remainder of the examination shows no abnormalities. An ECG shows diffuse ST elevations. Serum studies show a troponin I of 0.2 ng/mL (N < 0.01). Which of the following is the most likely cause of this patient's symptoms? Options: A. Cardiac tamponade B. Constrictive pericarditis C. Reinfarction D. Early infarct-associated pericarditis E. Dressler syndrome | E8: Answer: E Reasoning: The patient presents with chest pain, fever, a pericardial friction rub, and diffuse ST elevations two months after a myocardial infarction. This constellation of symptoms, especially the timing and the presence of a friction rub and diffuse ST elevations, is highly characteristic of Dressler syndrome (post-myocardial infarction syndrome), which is an autoimmune pericarditis occurring weeks to months after an MI. | F8: Dressler syndrome | G8: Yes | H8: 1 | I8: 1 | J8: 1 | K8: 1 | L8: 1 | M8: 0 | N8: 1 | O8: 0.5 | P8: =1-((ABS(H8-I8))+(ABS(J8-K8))+(ABS(L8-M8))+(ABS(N8-O8)))/4 -> 0.625 | U8: =(H8+J8+L8+N8)/4 -> 1 | V8: =(I8+K8+M8+O8)/4 -> 0.625
A9: CV_007 | B9: Gemini | C9: zero-shot | D9: A 4-year-old girl is brought to the physician with a 3-month history of progressive intermittent pain and swelling involving both knees, right ankle, and right wrist. The patient has been undergoing treatment with acetaminophen and ice packs, both of which relieved her symptoms. The affected joints feel "stuck” and are difficult to move immediately upon waking up in the morning. However, the patient can move her joints freely after a few minutes. She also complains of occasional mild eye pain that resolves spontaneously. Five months ago, she was diagnosed with an upper respiratory tract infection that resolved without treatment. Vital signs are within normal limits. Physical examination shows swollen and erythematous joints, which are tender to touch. Slit-lamp examination shows an anterior chamber flare with signs of iris inflammation bilaterally. Laboratory studies show: Blood parameters Hemoglobin 12.6 g/dL Leukocyte count 8,000/mm3 Segmented neutrophils 76% Eosinophils 1% Lymphocytes 20% Monocytes 3% Platelet count 360,000/mm3 Erythrocyte sedimentation rate 36 mm/hr Serum parameters Antinuclear antibodies 1:320 Rheumatoid factor negative Which of the following is the most likely diagnosis? Options: A. Acute lymphocytic leukemia B. Enthesitis-related arthritis C. Oligoarticular juvenile idiopathic arthritis D. Postinfectious arthritis E. Seronegative polyarticular juvenile idiopathic arthritis | E9: Answer: C Reasoning: The patient presents with chronic arthritis affecting 4 joints (both knees, right ankle, right wrist) in a young girl, which fits the definition of oligoarticular juvenile idiopathic arthritis. Key features supporting this diagnosis include morning stiffness, elevated ESR, positive ANA, negative RF, and chronic anterior uveitis, which is a common complication of ANA-positive oligoarticular JIA. Confidence: 100% | F9: Oligoarticular juvenile idiopathic arthritis | G9: Yes | H9: 1 | I9: 1 | J9: 1 | K9: 1 | L9: 0.5 | M9: 1 | N9: 1 | O9: 1 | P9: =1-((ABS(H9-I9))+(ABS(J9-K9))+(ABS(L9-M9))+(ABS(N9-O9)))/4 -> 0.875 | U9: =(H9+J9+L9+N9)/4 -> 0.875 | V9: =(I9+K9+M9+O9)/4 -> 1
A10: CV_008 | B10: Gemini | C10: zero-shot | D10: A 35-year-old is brought into the emergency room after a bicycle vs motored vehicle accident. He was unconscious after hitting the side of his head on the road, but recovered consciousness after a few minutes. He started to ride his bicycle again, but then developed a severe headache with nausea and vomiting, at which time he called EMS. While in the hospital, the patient is confused and cannot provide a history. He quickly loses consciousness and his CT scan is displayed in Figure 1. What is the most likely diagnosis? Options: A. Subarachnoid hemorrhage B. Subdural hematoma C. Epidural hematoma D. Subgaleal hematoma E. Caput succedaneum | E10: Answer: C Reasoning: The patient's presentation with initial loss of consciousness, followed by a period of lucidity, and then rapid neurological deterioration (severe headache, nausea, vomiting, confusion, and loss of consciousness) is the classic clinical picture of an epidural hematoma, often caused by a tear in the middle meningeal artery. Confidence: 100% | F10: Epidural hematoma | G10: Yes | H10: 1 | I10: 1 | J10: 1 | K10: 1 | L10: 0.5 | M10: 1 | N10: 1 | O10: 1 | P10: =1-((ABS(H10-I10))+(ABS(J10-K10))+(ABS(L10-M10))+(ABS(N10-O10)))/4 -> 0.875 | U10: =(H10+J10+L10+N10)/4 -> 0.875 | V10: =(I10+K10+M10+O10)/4 -> 1
A11: CV_009 | B11: Gemini | C11: zero-shot | D11: A 79-year-old man is admitted to the intensive care unit for hospital acquired pneumonia, a COPD flare, and acute heart failure requiring intubation and mechanical ventilation. On his first night in the intensive care unit, his temperature is 99.7°F (37.6°C), blood pressure is 107/58 mm Hg, and pulse is 150/min which is a sudden change from his previous vitals. Physical exam is notable for jugular venous distension and a rapid heart rate. The ventilator is checked and is functioning normally. Which of the following is the best next step in management for the most likely diagnosis? Options: A. Chest radiograph B. FAST exam C. Needle thoracostomy D. Thoracotomy E. Tube thoracostomy | E11: Answer: C Reasoning: The patient's sudden onset tachycardia, jugular venous distension, and borderline hypotension in the setting of mechanical ventilation strongly suggest a tension pneumothorax, which is a life-threatening emergency. Needle thoracostomy is the immediate, life-saving intervention to decompress the pleural space and relieve the tension. Confidence: 100% | F11: Needle thoracostomy | G11: Yes | H11: 1 | I11: 1 | J11: 1 | K11: 1 | L11: 1 | M11: 1 | N11: 1 | O11: 1 | P11: =1-((ABS(H11-I11))+(ABS(J11-K11))+(ABS(L11-M11))+(ABS(N11-O11)))/4 -> 1 | U11: =(H11+J11+L11+N11)/4 -> 1 | V11: =(I11+K11+M11+O11)/4 -> 1
A12: CV_010 | B12: Gemini | C12: zero-shot | D12: A primigravida, 29-year-old woman presents in her 28th week of pregnancy for evaluation of 3 hours of vaginal bleeding and abdominal pain. She denies any trauma and states that this is the first time she has had such symptoms. Her prenatal care has been optimal and all of her antenatal screenings have been within normal limits. Her vital signs are unremarkable. Physical examination reveals a small amount of blood in the vaginal canal and the cervical os is closed. Ultrasound imaging demonstrates positive fetal cardiac activity. What is the most likely diagnosis? Options: A. Complete abortion B. Incomplete abortion C. Inevitable abortion D. Missed abortion E. Threatened abortion | E12: Answer: E Reasoning: The patient presents with vaginal bleeding and abdominal pain at 28 weeks gestation, but her cervical os is closed and fetal cardiac activity is positive. This clinical picture, characterized by bleeding with a viable fetus and a closed cervix, is consistent with a threatened abortion, even though the term is more commonly applied to earlier gestations. Other types of abortion (complete, incomplete, inevitable, missed) are ruled out by the presence of a viable fetus and a closed cervix. Confidence: 100% | F12: Threatened abortion | G12: Yes | H12: 1 | I12: 1 | J12: 1 | K12: 1 | L12: 0.5 | M12: 1 | N12: 1 | O12: 1 | P12: =1-((ABS(H12-I12))+(ABS(J12-K12))+(ABS(L12-M12))+(ABS(N12-O12)))/4 -> 0.875 | U12: =(H12+J12+L12+N12)/4 -> 0.875 | V12: =(I12+K12+M12+O12)/4 -> 1
A13: CV_011 | B13: Gemini | C13: zero-shot | D13: A 34-year-old woman comes to the emergency department because of right flank pain and vomiting for 5 hours. She has had fever and chills for the past 2 days. She attended a barbecue 3 days ago, where she ate egg salad. She underwent surgery for left ovarian torsion a year ago. Menses occur at regular 28-day intervals and last 5 days. She is sexually active with 2 male partners and uses condoms inconsistently. Her only medication is an oral contraceptive pill. She is 163 cm (5 ft 4 in) tall and weighs 72.5 kg (160 lb); BMI is 27.5 kg/m2. She appears uncomfortable. Her temperature is 38.9°C (102°F), pulse is 101/min, and blood pressure is 118/76 mm Hg. The lungs are clear to auscultation. The right lower quadrant and right flank show severe tenderness to palpation. Pelvic examination shows no abnormalities. Laboratory studies show: Hemoglobin 12.8 g/dL Leukocyte count 14,200/mm3 Platelet count 230,000/mm3 Serum Na+ 136 mEq/L K+ 3.8 mEq/L Cl- 103 mEq/L Urea nitrogen 23 mg/dL Creatinine 1.2 mg/dL Urine Blood 1+ Protein 1+ Glucose negative Leukocyte esterase positive Nitrites negative RBC 6–8/hpf WBC 80–85/hpf Which of the following is the most likely diagnosis?" Options: A. Ovarian torsion B. Gastroenteritis C. Urethritis D. Pelvic inflammatory disease E. Pyelonephritis | E13: Answer: E Reasoning: The patient presents with classic symptoms of pyelonephritis, including fever, chills, right flank pain, vomiting, and right flank tenderness. Laboratory findings support this diagnosis with leukocytosis and significant pyuria (WBCs 80-85/hpf, positive leukocyte esterase) on urinalysis. | F13: Pyelonephritis | G13: Yes | H13: 1 | I13: 1 | J13: 1 | K13: 1 | L13: 1 | M13: 0 | N13: 1 | O13: 1 | P13: =1-((ABS(H13-I13))+(ABS(J13-K13))+(ABS(L13-M13))+(ABS(N13-O13)))/4 -> 0.75 | U13: =(H13+J13+L13+N13)/4 -> 1 | V13: =(I13+K13+M13+O13)/4 -> 0.75
A14: CV_012 | B14: Gemini | C14: zero-shot | D14: A 47-year-old woman presents with intermittent throbbing headaches. She says that she has had at least 1–2 every week for the last 3 months. She describes the pain as severe, pulsatile, and localized to the right frontotemporal and periorbital areas. She says the headaches usually last for several hours and are made worse by the presence of light. She endorses nausea with occasional vomiting during the most severe episodes. She denies any seizures, loss of consciousness, or focal neurologic deficits. Her past medical history is significant for myocardial infarction (MI) 1 year ago, status post percutaneous transluminal coronary angioplasty complicated by residual angina, and severe asthma, managed medically. The patient is afebrile, and the vital signs are within normal limits. A physical examination is unremarkable. A noncontrast computed tomography (CT) scan of the head appears normal. Which of the following is the best prophylactic treatment for this patient’s most likely diagnosis? Options: A. Sumatriptan B. Amitriptyline C. Valproic acid D. Propranolol E. Ibuprofen | E14: Answer: C Reasoning: The patient's symptoms are classic for migraine. Prophylactic treatment is indicated due to frequency. Sumatriptan is an acute treatment and contraindicated due to MI. Propranolol is contraindicated due to severe asthma. Ibuprofen is not a primary prophylactic agent. Valproic acid is an effective prophylactic agent for migraine and is generally safe in patients with a history of MI and asthma, making it a better choice than amitriptyline, which can have cardiac side effects (e.g., QT prolongation, orthostatic hypotension) that might be concerning in a patient with a history of MI and angina. Confidence: 95% | F14: Valproic acid | G14: Yes | H14: 0.5 | I14: 1 | J14: 1 | K14: 1 | L14: 0.5 | M14: 1 | N14: 0.5 | O14: 1 | P14: =1-((ABS(H14-I14))+(ABS(J14-K14))+(ABS(L14-M14))+(ABS(N14-O14)))/4 -> 0.625 | U14: =(H14+J14+L14+N14)/4 -> 0.625 | V14: =(I14+K14+M14+O14)/4 -> 1
A15: CV_013 | B15: Gemini | C15: zero-shot | D15: A 51-year-old woman presents the following significant and unintentional weight loss. She denies any personal history of blood clots in her past, but she says that her mother has also had to be treated for pulmonary embolism in the recent past. She also mentions that she had been struggling with her weight, so she was initially content with losing the weight, but her daughter convinced her to come to the office to be checked out. Her past medical history is significant for preeclampsia, hypertension, polycystic ovarian syndrome, and hypercholesterolemia. She currently smokes 1 pack of cigarettes per day, drinks a glass of wine per day, and she currently denies any illicit drug use, although she has a remote past of injection drug use with heroin. The vital signs include: temperature 36.7°C (98.0°F), blood pressure 126/74 mm Hg, heart rate 111/min and irregular, and respiratory rate 17/min. On physical examination, her pulses are bounding and complexion is pale, but breath sounds remain clear. Oxygen saturation was initially 91% on room air and electrocardiogram (ECG) showed atrial fibrillation. Upon further discussion with the patient, her physician discovers that she is having some cognitive difficulty. Her leukocyte count is elevated to 128,000/mm3, and she has elevated lactate dehydrogenase (LDH), uric acid, and B-12 levels. A BCR-ABL translocation is present, as evidenced by the Philadelphia chromosome. What is the most likely diagnosis for this patient? Options: A. Acute lymphocytic leukemia B. Acute myelogenous leukemia C. Chronic lymphocytic leukemia D. Chronic myelogenous leukemia E. Hairy cell leukemia | E15: Answer: D Reasoning: The presence of a markedly elevated leukocyte count (128,000/mm3), elevated lactate dehydrogenase (LDH) and uric acid, and the definitive finding of the Philadelphia chromosome (BCR-ABL translocation) are classic diagnostic features of Chronic Myelogenous Leukemia (CML). Confidence: 100% | F15: Chronic myelogenous leukemia | G15: Yes | H15: 1 | I15: 1 | J15: 0.5 | K15: 1 | L15: 1 | M15: 1 | N15: 1 | O15: 1 | P15: =1-((ABS(H15-I15))+(ABS(J15-K15))+(ABS(L15-M15))+(ABS(N15-O15)))/4 -> 0.875 | U15: =(H15+J15+L15+N15)/4 -> 0.875 | V15: =(I15+K15+M15+O15)/4 -> 1
... A152: CV_050 | B152: Gemini | C152: chain-of-thought | D152: A 2-month-old infant is brought in by his mother for runny nose and cough. She reports he had an ear infection 2 weeks ago, and since then he has had a productive cough and nasal congestion. His medical history is significant for multiple ear infections and eczematous dermatitis. He has also been hospitalized for 2 episodes of severe viral bronchiolitis. The mother reports that the infant has a good appetite but has had intermittent, non-bloody diarrhea. The patient is at the 20th percentile for weight. On physical examination, the patient has widespread, dry, erythematous patches, mucopurulent nasal drip, and crusting of the nares. His tongue is coated by a thick white film which is easily scraped off. Crackles are heard at the left lung base. Labs are drawn, as shown below: Hemoglobin: 12.8 g/dL Platelets: 280,000/mm^3 Leukocytes: 7,500/mm^3 Neutrophils: 5,500/mm^3 Lymphocytes: 2,000/mm^3 Serum: Na+: 138 mEq/L Cl-: 96 mEq/L K+: 4.3 mEq/L HCO3-: 23 mEq/L Urea nitrogen: 18 mg/dL Glucose: 90 mg/dL Creatinine: 1.0 mg/dL Ca2+: : 9.2 mg/dL Which of the following is the most likely cause of this patient’s presentation? Options: A. 22q11.2 deletion B. Adenosine deaminase deficiency C. Defective leukocyte adhesion D. Defective tyrosine kinase E. WAS gene mutation | E152: Reasoning: This 2-month-old infant presents with a severe and diverse pattern of recurrent infections, including multiple ear infections, two hospitalizations for severe viral bronchiolitis, and current oral thrush (a fungal infection). He also has eczematous dermatitis and intermittent diarrhea, with weight at the 20th percentile. This constellation of severe, recurrent viral, bacterial, and fungal infections, along with eczema and poor weight gain, is highly suggestive of a severe combined immunodeficiency (SCID). Let's evaluate the options: * **A. 22q11.2 deletion (DiGeorge Syndrome):** Causes T-cell deficiency, but typically presents with hypocalcemia and cardiac defects, neither of which are present (normal Ca2+). While some forms can be partial, the overall picture fits SCID better. * **B. Adenosine deaminase deficiency (ADA deficiency):** This is a common cause of SCID, characterized by severe T-cell and B-cell dysfunction. The patient's presentation of severe, recurrent viral, bacterial, and fungal infections, eczema, and diarrhea is highly consistent with SCID. Although the absolute lymphocyte count (2000/mm^3) is not profoundly low (<500), it is on the lower side for a 2-month-old and does not rule out SCID, especially given the severe clinical picture. * **C. Defective leukocyte adhesion (LAD):** Characterized by recurrent bacterial infections, impaired wound healing, and delayed umbilical cord separation, with marked leukocytosis (neutrophilia). The patient's normal leukocyte count and severe viral/fungal infections make LAD unlikely. * **D. Defective tyrosine kinase (X-linked agammaglobulinemia - XLA):** Causes B-cell deficiency and recurrent bacterial infections, typically presenting after 6 months of age. The severe viral and fungal infections, and the early onset, are not typical for XLA. * **E. WAS gene mutation (Wiskott-Aldrich Syndrome):** Characterized by eczema, recurrent infections, and thrombocytopenia with small platelets. The patient has eczema and recurrent infections, but a normal platelet count (280,000/mm^3) rules out WAS. Given the severe, diverse, and recurrent infections affecting multiple systems (respiratory, GI, skin, oral mucosa), ADA deficiency, as a form of SCID, is the most likely diagnosis. The final answer is $\boxed{B}$ Confidence: 95% | F152: Adenosine deaminase deficiency | G152: No | H152: 1 | I152: 1 | J152: 1 | K152: 1 | L152: 1 | M152: 1 | N152: 1 | O152: 1 | P152: =1-((ABS(H152-I152))+(ABS(J152-K152))+(ABS(L152-M152))+(ABS(N152-O152)))/4 -> 1 | U152: =(H152+J152+L152+N152)/4 -> 1 | V152: =(I152+K152+M152+O152)/4 -> 1
